[
	{
		"config": {
			"margin_of_error": [
				-0.1,
				0.5
			],
			"threshold": 0.5,
			"epoch": "best",
			"min_talk_len": null,
			"random_baseline": {}
		},
		"totals": {
			"eval": {
				"selected": 5778,
				"relevant": 5778,
				"true_positives": 135,
				"false_positives": 5643,
				"false_negatives": 5643,
				"precision": 0.02336448598130841,
				"recall": 0.02336448598130841,
				"f1_score": 0.02336448598130841
			},
			"valid": {
				"selected": 5048,
				"relevant": 5048,
				"true_positives": 156,
				"false_positives": 4892,
				"false_negatives": 4892,
				"precision": 0.030903328050713153,
				"recall": 0.030903328050713153,
				"f1_score": 0.030903328050713153
			}
		}
	},
	{
		"config": {
			"margin_of_error": [
				-0.1,
				0.5
			],
			"threshold": 0.5,
			"epoch": "best",
			"min_talk_len": 0,
			"random_baseline": {}
		},
		"totals": {
			"eval": {
				"selected": 2736,
				"relevant": 5557,
				"true_positives": 132,
				"false_positives": 2604,
				"false_negatives": 5425,
				"precision": 0.04824561403508772,
				"recall": 0.0237538240057585,
				"f1_score": 0.03183407693235259
			},
			"valid": {
				"selected": 2344,
				"relevant": 4865,
				"true_positives": 120,
				"false_positives": 2224,
				"false_negatives": 4745,
				"precision": 0.051194539249146756,
				"recall": 0.024665981500513873,
				"f1_score": 0.033291718684977115
			}
		}
	},
	{
		"config": {
			"margin_of_error": [
				-0.1,
				0.5
			],
			"threshold": 0.5,
			"epoch": "best",
			"min_talk_len": 5,
			"random_baseline": {}
		},
		"totals": {
			"eval": {
				"selected": 2438,
				"relevant": 5192,
				"true_positives": 138,
				"false_positives": 2300,
				"false_negatives": 5054,
				"precision": 0.05660377358490566,
				"recall": 0.026579352850539292,
				"f1_score": 0.036173001310615994
			},
			"valid": {
				"selected": 2126,
				"relevant": 4567,
				"true_positives": 118,
				"false_positives": 2008,
				"false_negatives": 4449,
				"precision": 0.055503292568203196,
				"recall": 0.025837530107291437,
				"f1_score": 0.03526072015538622
			}
		}
	},
	{
		"config": {
			"margin_of_error": [
				-0.1,
				0.5
			],
			"threshold": 0.5,
			"epoch": "best",
			"min_talk_len": 10,
			"random_baseline": {}
		},
		"totals": {
			"eval": {
				"selected": 2116,
				"relevant": 4361,
				"true_positives": 116,
				"false_positives": 2000,
				"false_negatives": 4245,
				"precision": 0.054820415879017016,
				"recall": 0.026599403806466408,
				"f1_score": 0.03581905203026092
			},
			"valid": {
				"selected": 1755,
				"relevant": 3804,
				"true_positives": 114,
				"false_positives": 1641,
				"false_negatives": 3690,
				"precision": 0.06495726495726496,
				"recall": 0.02996845425867508,
				"f1_score": 0.041014570966001085
			}
		}
	},
	{
		"config": {
			"margin_of_error": [
				-0.1,
				0.5
			],
			"threshold": 0.6,
			"epoch": "best",
			"min_talk_len": null,
			"random_baseline": {}
		},
		"totals": {
			"eval": {
				"selected": 5778,
				"relevant": 5778,
				"true_positives": 171,
				"false_positives": 5607,
				"false_negatives": 5607,
				"precision": 0.029595015576323987,
				"recall": 0.029595015576323987,
				"f1_score": 0.029595015576323987
			},
			"valid": {
				"selected": 5048,
				"relevant": 5048,
				"true_positives": 125,
				"false_positives": 4923,
				"false_negatives": 4923,
				"precision": 0.02476228209191759,
				"recall": 0.02476228209191759,
				"f1_score": 0.02476228209191759
			}
		}
	},
	{
		"config": {
			"margin_of_error": [
				-0.1,
				0.5
			],
			"threshold": 0.6,
			"epoch": "best",
			"min_talk_len": 0,
			"random_baseline": {}
		},
		"totals": {
			"eval": {
				"selected": 2692,
				"relevant": 5557,
				"true_positives": 139,
				"false_positives": 2553,
				"false_negatives": 5418,
				"precision": 0.05163447251114413,
				"recall": 0.025013496490912362,
				"f1_score": 0.03370105467329373
			},
			"valid": {
				"selected": 2397,
				"relevant": 4865,
				"true_positives": 115,
				"false_positives": 2282,
				"false_negatives": 4750,
				"precision": 0.047976637463496036,
				"recall": 0.023638232271325797,
				"f1_score": 0.03167171578077664
			}
		}
	},
	{
		"config": {
			"margin_of_error": [
				-0.1,
				0.5
			],
			"threshold": 0.6,
			"epoch": "best",
			"min_talk_len": 5,
			"random_baseline": {}
		},
		"totals": {
			"eval": {
				"selected": 2451,
				"relevant": 5192,
				"true_positives": 130,
				"false_positives": 2321,
				"false_negatives": 5062,
				"precision": 0.053039575683394534,
				"recall": 0.025038520801232665,
				"f1_score": 0.03401805573727594
			},
			"valid": {
				"selected": 2133,
				"relevant": 4567,
				"true_positives": 123,
				"false_positives": 2010,
				"false_negatives": 4444,
				"precision": 0.057665260196905765,
				"recall": 0.026932340705058025,
				"f1_score": 0.03671641791044776
			}
		}
	},
	{
		"config": {
			"margin_of_error": [
				-0.1,
				0.5
			],
			"threshold": 0.6,
			"epoch": "best",
			"min_talk_len": 10,
			"random_baseline": {}
		},
		"totals": {
			"eval": {
				"selected": 2076,
				"relevant": 4361,
				"true_positives": 121,
				"false_positives": 1955,
				"false_negatives": 4240,
				"precision": 0.05828516377649326,
				"recall": 0.0277459298326072,
				"f1_score": 0.037595153021593906
			},
			"valid": {
				"selected": 1759,
				"relevant": 3804,
				"true_positives": 99,
				"false_positives": 1660,
				"false_negatives": 3705,
				"precision": 0.056281978396816375,
				"recall": 0.026025236593059938,
				"f1_score": 0.03559230630954521
			}
		}
	},
	{
		"config": {
			"margin_of_error": [
				-0.1,
				0.5
			],
			"threshold": 0.65,
			"epoch": "best",
			"min_talk_len": null,
			"random_baseline": {}
		},
		"totals": {
			"eval": {
				"selected": 5778,
				"relevant": 5778,
				"true_positives": 151,
				"false_positives": 5627,
				"false_negatives": 5627,
				"precision": 0.02613361024575978,
				"recall": 0.02613361024575978,
				"f1_score": 0.02613361024575978
			},
			"valid": {
				"selected": 5048,
				"relevant": 5048,
				"true_positives": 160,
				"false_positives": 4888,
				"false_negatives": 4888,
				"precision": 0.03169572107765452,
				"recall": 0.03169572107765452,
				"f1_score": 0.03169572107765452
			}
		}
	},
	{
		"config": {
			"margin_of_error": [
				-0.1,
				0.5
			],
			"threshold": 0.65,
			"epoch": "best",
			"min_talk_len": 0,
			"random_baseline": {}
		},
		"totals": {
			"eval": {
				"selected": 2748,
				"relevant": 5557,
				"true_positives": 150,
				"false_positives": 2598,
				"false_negatives": 5407,
				"precision": 0.05458515283842795,
				"recall": 0.026992981824725572,
				"f1_score": 0.03612281757977122
			},
			"valid": {
				"selected": 2366,
				"relevant": 4865,
				"true_positives": 141,
				"false_positives": 2225,
				"false_negatives": 4724,
				"precision": 0.05959425190194421,
				"recall": 0.028982528263103803,
				"f1_score": 0.038998755358871526
			}
		}
	},
	{
		"config": {
			"margin_of_error": [
				-0.1,
				0.5
			],
			"threshold": 0.65,
			"epoch": "best",
			"min_talk_len": 5,
			"random_baseline": {}
		},
		"totals": {
			"eval": {
				"selected": 2524,
				"relevant": 5192,
				"true_positives": 150,
				"false_positives": 2374,
				"false_negatives": 5042,
				"precision": 0.059429477020602216,
				"recall": 0.02889060092449923,
				"f1_score": 0.03888024883359254
			},
			"valid": {
				"selected": 2166,
				"relevant": 4567,
				"true_positives": 137,
				"false_positives": 2029,
				"false_negatives": 4430,
				"precision": 0.06325023084025855,
				"recall": 0.029997810378804467,
				"f1_score": 0.040695083915045296
			}
		}
	},
	{
		"config": {
			"margin_of_error": [
				-0.1,
				0.5
			],
			"threshold": 0.65,
			"epoch": "best",
			"min_talk_len": 10,
			"random_baseline": {}
		},
		"totals": {
			"eval": {
				"selected": 2119,
				"relevant": 4361,
				"true_positives": 123,
				"false_positives": 1996,
				"false_negatives": 4238,
				"precision": 0.05804624823029731,
				"recall": 0.028204540243063517,
				"f1_score": 0.03796296296296296
			},
			"valid": {
				"selected": 1814,
				"relevant": 3804,
				"true_positives": 98,
				"false_positives": 1716,
				"false_negatives": 3706,
				"precision": 0.05402425578831312,
				"recall": 0.02576235541535226,
				"f1_score": 0.034887860448558204
			}
		}
	},
	{
		"config": {
			"margin_of_error": [
				-0.1,
				0.5
			],
			"threshold": 0.7,
			"epoch": "best",
			"min_talk_len": null,
			"random_baseline": {}
		},
		"totals": {
			"eval": {
				"selected": 5778,
				"relevant": 5778,
				"true_positives": 154,
				"false_positives": 5624,
				"false_negatives": 5624,
				"precision": 0.02665282104534441,
				"recall": 0.02665282104534441,
				"f1_score": 0.02665282104534441
			},
			"valid": {
				"selected": 5048,
				"relevant": 5048,
				"true_positives": 151,
				"false_positives": 4897,
				"false_negatives": 4897,
				"precision": 0.02991283676703645,
				"recall": 0.02991283676703645,
				"f1_score": 0.02991283676703645
			}
		}
	},
	{
		"config": {
			"margin_of_error": [
				-0.1,
				0.5
			],
			"threshold": 0.7,
			"epoch": "best",
			"min_talk_len": 0,
			"random_baseline": {}
		},
		"totals": {
			"eval": {
				"selected": 2755,
				"relevant": 5557,
				"true_positives": 144,
				"false_positives": 2611,
				"false_negatives": 5413,
				"precision": 0.052268602540834846,
				"recall": 0.025913262551736548,
				"f1_score": 0.03464870067372473
			},
			"valid": {
				"selected": 2364,
				"relevant": 4865,
				"true_positives": 130,
				"false_positives": 2234,
				"false_negatives": 4735,
				"precision": 0.05499153976311337,
				"recall": 0.02672147995889003,
				"f1_score": 0.035966247060450963
			}
		}
	},
	{
		"config": {
			"margin_of_error": [
				-0.1,
				0.5
			],
			"threshold": 0.7,
			"epoch": "best",
			"min_talk_len": 5,
			"random_baseline": {}
		},
		"totals": {
			"eval": {
				"selected": 2453,
				"relevant": 5192,
				"true_positives": 130,
				"false_positives": 2323,
				"false_negatives": 5062,
				"precision": 0.05299633102323685,
				"recall": 0.025038520801232665,
				"f1_score": 0.034009156311314584
			},
			"valid": {
				"selected": 2177,
				"relevant": 4567,
				"true_positives": 120,
				"false_positives": 2057,
				"false_negatives": 4447,
				"precision": 0.05512172714745062,
				"recall": 0.026275454346398074,
				"f1_score": 0.03558718861209965
			}
		}
	},
	{
		"config": {
			"margin_of_error": [
				-0.1,
				0.5
			],
			"threshold": 0.7,
			"epoch": "best",
			"min_talk_len": 10,
			"random_baseline": {}
		},
		"totals": {
			"eval": {
				"selected": 2155,
				"relevant": 4361,
				"true_positives": 140,
				"false_positives": 2015,
				"false_negatives": 4221,
				"precision": 0.06496519721577726,
				"recall": 0.03210272873194221,
				"f1_score": 0.04297114794352363
			},
			"valid": {
				"selected": 1772,
				"relevant": 3804,
				"true_positives": 120,
				"false_positives": 1652,
				"false_negatives": 3684,
				"precision": 0.06772009029345373,
				"recall": 0.031545741324921134,
				"f1_score": 0.043041606886657105
			}
		}
	},
	{
		"config": {
			"margin_of_error": [
				-0.3,
				0.3
			],
			"threshold": 0.5,
			"epoch": "best",
			"min_talk_len": null,
			"random_baseline": {}
		},
		"totals": {
			"eval": {
				"selected": 5778,
				"relevant": 5778,
				"true_positives": 122,
				"false_positives": 5656,
				"false_negatives": 5656,
				"precision": 0.021114572516441676,
				"recall": 0.021114572516441676,
				"f1_score": 0.021114572516441676
			},
			"valid": {
				"selected": 5048,
				"relevant": 5048,
				"true_positives": 126,
				"false_positives": 4922,
				"false_negatives": 4922,
				"precision": 0.02496038034865293,
				"recall": 0.02496038034865293,
				"f1_score": 0.024960380348652934
			}
		}
	},
	{
		"config": {
			"margin_of_error": [
				-0.3,
				0.3
			],
			"threshold": 0.5,
			"epoch": "best",
			"min_talk_len": 0,
			"random_baseline": {}
		},
		"totals": {
			"eval": {
				"selected": 2663,
				"relevant": 5557,
				"true_positives": 166,
				"false_positives": 2497,
				"false_negatives": 5391,
				"precision": 0.06233571160345475,
				"recall": 0.029872233219362967,
				"f1_score": 0.040389294403892946
			},
			"valid": {
				"selected": 2320,
				"relevant": 4865,
				"true_positives": 135,
				"false_positives": 2185,
				"false_negatives": 4730,
				"precision": 0.05818965517241379,
				"recall": 0.02774922918807811,
				"f1_score": 0.037578288100208766
			}
		}
	},
	{
		"config": {
			"margin_of_error": [
				-0.3,
				0.3
			],
			"threshold": 0.5,
			"epoch": "best",
			"min_talk_len": 5,
			"random_baseline": {}
		},
		"totals": {
			"eval": {
				"selected": 2456,
				"relevant": 5192,
				"true_positives": 157,
				"false_positives": 2299,
				"false_negatives": 5035,
				"precision": 0.06392508143322476,
				"recall": 0.030238828967642527,
				"f1_score": 0.041056485355648535
			},
			"valid": {
				"selected": 2166,
				"relevant": 4567,
				"true_positives": 131,
				"false_positives": 2035,
				"false_negatives": 4436,
				"precision": 0.060480147737765465,
				"recall": 0.028684037661484564,
				"f1_score": 0.0389128174662112
			}
		}
	},
	{
		"config": {
			"margin_of_error": [
				-0.3,
				0.3
			],
			"threshold": 0.5,
			"epoch": "best",
			"min_talk_len": 10,
			"random_baseline": {}
		},
		"totals": {
			"eval": {
				"selected": 2098,
				"relevant": 4361,
				"true_positives": 116,
				"false_positives": 1982,
				"false_negatives": 4245,
				"precision": 0.055290753098188754,
				"recall": 0.026599403806466408,
				"f1_score": 0.03591887289054033
			},
			"valid": {
				"selected": 1735,
				"relevant": 3804,
				"true_positives": 118,
				"false_positives": 1617,
				"false_negatives": 3686,
				"precision": 0.06801152737752161,
				"recall": 0.031019978969505785,
				"f1_score": 0.042606968766925435
			}
		}
	},
	{
		"config": {
			"margin_of_error": [
				-0.3,
				0.3
			],
			"threshold": 0.6,
			"epoch": "best",
			"min_talk_len": null,
			"random_baseline": {}
		},
		"totals": {
			"eval": {
				"selected": 5778,
				"relevant": 5778,
				"true_positives": 141,
				"false_positives": 5637,
				"false_negatives": 5637,
				"precision": 0.024402907580477674,
				"recall": 0.024402907580477674,
				"f1_score": 0.024402907580477674
			},
			"valid": {
				"selected": 5048,
				"relevant": 5048,
				"true_positives": 123,
				"false_positives": 4925,
				"false_negatives": 4925,
				"precision": 0.02436608557844691,
				"recall": 0.02436608557844691,
				"f1_score": 0.02436608557844691
			}
		}
	},
	{
		"config": {
			"margin_of_error": [
				-0.3,
				0.3
			],
			"threshold": 0.6,
			"epoch": "best",
			"min_talk_len": 0,
			"random_baseline": {}
		},
		"totals": {
			"eval": {
				"selected": 2707,
				"relevant": 5557,
				"true_positives": 149,
				"false_positives": 2558,
				"false_negatives": 5408,
				"precision": 0.05504248245289989,
				"recall": 0.026813028612560734,
				"f1_score": 0.03606001936108422
			},
			"valid": {
				"selected": 2349,
				"relevant": 4865,
				"true_positives": 143,
				"false_positives": 2206,
				"false_negatives": 4722,
				"precision": 0.06087696892294593,
				"recall": 0.029393627954779036,
				"f1_score": 0.039645134460770726
			}
		}
	},
	{
		"config": {
			"margin_of_error": [
				-0.3,
				0.3
			],
			"threshold": 0.6,
			"epoch": "best",
			"min_talk_len": 5,
			"random_baseline": {}
		},
		"totals": {
			"eval": {
				"selected": 2496,
				"relevant": 5192,
				"true_positives": 128,
				"false_positives": 2368,
				"false_negatives": 5064,
				"precision": 0.05128205128205128,
				"recall": 0.02465331278890601,
				"f1_score": 0.03329864724245577
			},
			"valid": {
				"selected": 2086,
				"relevant": 4567,
				"true_positives": 122,
				"false_positives": 1964,
				"false_negatives": 4445,
				"precision": 0.058485139022051776,
				"recall": 0.026713378585504707,
				"f1_score": 0.0366751841274613
			}
		}
	},
	{
		"config": {
			"margin_of_error": [
				-0.3,
				0.3
			],
			"threshold": 0.6,
			"epoch": "best",
			"min_talk_len": 10,
			"random_baseline": {}
		},
		"totals": {
			"eval": {
				"selected": 2136,
				"relevant": 4361,
				"true_positives": 119,
				"false_positives": 2017,
				"false_negatives": 4242,
				"precision": 0.05571161048689138,
				"recall": 0.027287319422150885,
				"f1_score": 0.03663229182699708
			},
			"valid": {
				"selected": 1778,
				"relevant": 3804,
				"true_positives": 104,
				"false_positives": 1674,
				"false_negatives": 3700,
				"precision": 0.05849268841394826,
				"recall": 0.027339642481598318,
				"f1_score": 0.03726262988176281
			}
		}
	},
	{
		"config": {
			"margin_of_error": [
				-0.3,
				0.3
			],
			"threshold": 0.65,
			"epoch": "best",
			"min_talk_len": null,
			"random_baseline": {}
		},
		"totals": {
			"eval": {
				"selected": 5778,
				"relevant": 5778,
				"true_positives": 157,
				"false_positives": 5621,
				"false_negatives": 5621,
				"precision": 0.027172031844929043,
				"recall": 0.027172031844929043,
				"f1_score": 0.027172031844929043
			},
			"valid": {
				"selected": 5048,
				"relevant": 5048,
				"true_positives": 149,
				"false_positives": 4899,
				"false_negatives": 4899,
				"precision": 0.02951664025356577,
				"recall": 0.02951664025356577,
				"f1_score": 0.02951664025356577
			}
		}
	},
	{
		"config": {
			"margin_of_error": [
				-0.3,
				0.3
			],
			"threshold": 0.65,
			"epoch": "best",
			"min_talk_len": 0,
			"random_baseline": {}
		},
		"totals": {
			"eval": {
				"selected": 2788,
				"relevant": 5557,
				"true_positives": 131,
				"false_positives": 2657,
				"false_negatives": 5426,
				"precision": 0.046987087517934005,
				"recall": 0.023573870793593667,
				"f1_score": 0.03139604553624925
			},
			"valid": {
				"selected": 2458,
				"relevant": 4865,
				"true_positives": 136,
				"false_positives": 2322,
				"false_negatives": 4729,
				"precision": 0.05532953620829943,
				"recall": 0.027954779033915723,
				"f1_score": 0.037143247303017886
			}
		}
	},
	{
		"config": {
			"margin_of_error": [
				-0.3,
				0.3
			],
			"threshold": 0.65,
			"epoch": "best",
			"min_talk_len": 5,
			"random_baseline": {}
		},
		"totals": {
			"eval": {
				"selected": 2476,
				"relevant": 5192,
				"true_positives": 138,
				"false_positives": 2338,
				"false_negatives": 5054,
				"precision": 0.05573505654281099,
				"recall": 0.026579352850539292,
				"f1_score": 0.03599374021909234
			},
			"valid": {
				"selected": 2161,
				"relevant": 4567,
				"true_positives": 144,
				"false_positives": 2017,
				"false_negatives": 4423,
				"precision": 0.06663581675150393,
				"recall": 0.03153054521567769,
				"f1_score": 0.04280618311533889
			}
		}
	},
	{
		"config": {
			"margin_of_error": [
				-0.3,
				0.3
			],
			"threshold": 0.65,
			"epoch": "best",
			"min_talk_len": 10,
			"random_baseline": {}
		},
		"totals": {
			"eval": {
				"selected": 2113,
				"relevant": 4361,
				"true_positives": 113,
				"false_positives": 2000,
				"false_negatives": 4248,
				"precision": 0.05347846663511595,
				"recall": 0.025911488190781932,
				"f1_score": 0.03490886623416744
			},
			"valid": {
				"selected": 1839,
				"relevant": 3804,
				"true_positives": 120,
				"false_positives": 1719,
				"false_negatives": 3684,
				"precision": 0.06525285481239804,
				"recall": 0.031545741324921134,
				"f1_score": 0.04253056884635832
			}
		}
	},
	{
		"config": {
			"margin_of_error": [
				-0.3,
				0.3
			],
			"threshold": 0.7,
			"epoch": "best",
			"min_talk_len": null,
			"random_baseline": {}
		},
		"totals": {
			"eval": {
				"selected": 5778,
				"relevant": 5778,
				"true_positives": 153,
				"false_positives": 5625,
				"false_negatives": 5625,
				"precision": 0.0264797507788162,
				"recall": 0.0264797507788162,
				"f1_score": 0.026479750778816195
			},
			"valid": {
				"selected": 5048,
				"relevant": 5048,
				"true_positives": 156,
				"false_positives": 4892,
				"false_negatives": 4892,
				"precision": 0.030903328050713153,
				"recall": 0.030903328050713153,
				"f1_score": 0.030903328050713153
			}
		}
	},
	{
		"config": {
			"margin_of_error": [
				-0.3,
				0.3
			],
			"threshold": 0.7,
			"epoch": "best",
			"min_talk_len": 0,
			"random_baseline": {}
		},
		"totals": {
			"eval": {
				"selected": 2716,
				"relevant": 5557,
				"true_positives": 147,
				"false_positives": 2569,
				"false_negatives": 5410,
				"precision": 0.05412371134020619,
				"recall": 0.026453122188231058,
				"f1_score": 0.03553728997945123
			},
			"valid": {
				"selected": 2354,
				"relevant": 4865,
				"true_positives": 119,
				"false_positives": 2235,
				"false_negatives": 4746,
				"precision": 0.05055225148683093,
				"recall": 0.02446043165467626,
				"f1_score": 0.03296855520155146
			}
		}
	},
	{
		"config": {
			"margin_of_error": [
				-0.3,
				0.3
			],
			"threshold": 0.7,
			"epoch": "best",
			"min_talk_len": 5,
			"random_baseline": {}
		},
		"totals": {
			"eval": {
				"selected": 2436,
				"relevant": 5192,
				"true_positives": 145,
				"false_positives": 2291,
				"false_negatives": 5047,
				"precision": 0.05952380952380952,
				"recall": 0.02792758089368259,
				"f1_score": 0.03801782905086523
			},
			"valid": {
				"selected": 2175,
				"relevant": 4567,
				"true_positives": 119,
				"false_positives": 2056,
				"false_negatives": 4448,
				"precision": 0.05471264367816092,
				"recall": 0.026056492226844755,
				"f1_score": 0.03530109759715218
			}
		}
	},
	{
		"config": {
			"margin_of_error": [
				-0.3,
				0.3
			],
			"threshold": 0.7,
			"epoch": "best",
			"min_talk_len": 10,
			"random_baseline": {}
		},
		"totals": {
			"eval": {
				"selected": 2077,
				"relevant": 4361,
				"true_positives": 125,
				"false_positives": 1952,
				"false_negatives": 4236,
				"precision": 0.0601829561868079,
				"recall": 0.028663150653519834,
				"f1_score": 0.038831935383659526
			},
			"valid": {
				"selected": 1769,
				"relevant": 3804,
				"true_positives": 120,
				"false_positives": 1649,
				"false_negatives": 3684,
				"precision": 0.06783493499152063,
				"recall": 0.031545741324921134,
				"f1_score": 0.04306477660147138
			}
		}
	},
	{
		"config": {
			"margin_of_error": [
				-0.5,
				0.5
			],
			"threshold": 0.5,
			"epoch": "best",
			"min_talk_len": null,
			"random_baseline": {}
		},
		"totals": {
			"eval": {
				"selected": 5778,
				"relevant": 5778,
				"true_positives": 261,
				"false_positives": 5517,
				"false_negatives": 5517,
				"precision": 0.045171339563862926,
				"recall": 0.045171339563862926,
				"f1_score": 0.04517133956386293
			},
			"valid": {
				"selected": 5048,
				"relevant": 5048,
				"true_positives": 238,
				"false_positives": 4810,
				"false_negatives": 4810,
				"precision": 0.04714738510301109,
				"recall": 0.04714738510301109,
				"f1_score": 0.047147385103011086
			}
		}
	},
	{
		"config": {
			"margin_of_error": [
				-0.5,
				0.5
			],
			"threshold": 0.5,
			"epoch": "best",
			"min_talk_len": 0,
			"random_baseline": {}
		},
		"totals": {
			"eval": {
				"selected": 2734,
				"relevant": 5557,
				"true_positives": 275,
				"false_positives": 2459,
				"false_negatives": 5282,
				"precision": 0.1005852231163131,
				"recall": 0.04948713334533021,
				"f1_score": 0.06633699191894826
			},
			"valid": {
				"selected": 2322,
				"relevant": 4865,
				"true_positives": 207,
				"false_positives": 2115,
				"false_negatives": 4658,
				"precision": 0.08914728682170543,
				"recall": 0.04254881808838643,
				"f1_score": 0.05760400723528593
			}
		}
	},
	{
		"config": {
			"margin_of_error": [
				-0.5,
				0.5
			],
			"threshold": 0.5,
			"epoch": "best",
			"min_talk_len": 5,
			"random_baseline": {}
		},
		"totals": {
			"eval": {
				"selected": 2480,
				"relevant": 5192,
				"true_positives": 204,
				"false_positives": 2276,
				"false_negatives": 4988,
				"precision": 0.08225806451612903,
				"recall": 0.039291217257318954,
				"f1_score": 0.05318039624608968
			},
			"valid": {
				"selected": 2163,
				"relevant": 4567,
				"true_positives": 221,
				"false_positives": 1942,
				"false_negatives": 4346,
				"precision": 0.10217290799815072,
				"recall": 0.04839062842128312,
				"f1_score": 0.06567607726597326
			}
		}
	},
	{
		"config": {
			"margin_of_error": [
				-0.5,
				0.5
			],
			"threshold": 0.5,
			"epoch": "best",
			"min_talk_len": 10,
			"random_baseline": {}
		},
		"totals": {
			"eval": {
				"selected": 2004,
				"relevant": 4361,
				"true_positives": 183,
				"false_positives": 1821,
				"false_negatives": 4178,
				"precision": 0.09131736526946108,
				"recall": 0.04196285255675304,
				"f1_score": 0.057501963864886096
			},
			"valid": {
				"selected": 1764,
				"relevant": 3804,
				"true_positives": 170,
				"false_positives": 1594,
				"false_negatives": 3634,
				"precision": 0.0963718820861678,
				"recall": 0.04468980021030494,
				"f1_score": 0.0610632183908046
			}
		}
	},
	{
		"config": {
			"margin_of_error": [
				-0.5,
				0.5
			],
			"threshold": 0.6,
			"epoch": "best",
			"min_talk_len": null,
			"random_baseline": {}
		},
		"totals": {
			"eval": {
				"selected": 5778,
				"relevant": 5778,
				"true_positives": 241,
				"false_positives": 5537,
				"false_negatives": 5537,
				"precision": 0.04170993423329872,
				"recall": 0.04170993423329872,
				"f1_score": 0.04170993423329872
			},
			"valid": {
				"selected": 5048,
				"relevant": 5048,
				"true_positives": 224,
				"false_positives": 4824,
				"false_negatives": 4824,
				"precision": 0.044374009508716325,
				"recall": 0.044374009508716325,
				"f1_score": 0.04437400950871633
			}
		}
	},
	{
		"config": {
			"margin_of_error": [
				-0.5,
				0.5
			],
			"threshold": 0.6,
			"epoch": "best",
			"min_talk_len": 0,
			"random_baseline": {}
		},
		"totals": {
			"eval": {
				"selected": 2722,
				"relevant": 5557,
				"true_positives": 245,
				"false_positives": 2477,
				"false_negatives": 5312,
				"precision": 0.09000734753857458,
				"recall": 0.0440885369803851,
				"f1_score": 0.05918589201594395
			},
			"valid": {
				"selected": 2382,
				"relevant": 4865,
				"true_positives": 227,
				"false_positives": 2155,
				"false_negatives": 4638,
				"precision": 0.09529806884970612,
				"recall": 0.046659815005138744,
				"f1_score": 0.06264661239133433
			}
		}
	},
	{
		"config": {
			"margin_of_error": [
				-0.5,
				0.5
			],
			"threshold": 0.6,
			"epoch": "best",
			"min_talk_len": 5,
			"random_baseline": {}
		},
		"totals": {
			"eval": {
				"selected": 2432,
				"relevant": 5192,
				"true_positives": 248,
				"false_positives": 2184,
				"false_negatives": 4944,
				"precision": 0.10197368421052631,
				"recall": 0.04776579352850539,
				"f1_score": 0.06505771248688352
			},
			"valid": {
				"selected": 2166,
				"relevant": 4567,
				"true_positives": 201,
				"false_positives": 1965,
				"false_negatives": 4366,
				"precision": 0.09279778393351801,
				"recall": 0.04401138603021677,
				"f1_score": 0.05970592603594238
			}
		}
	},
	{
		"config": {
			"margin_of_error": [
				-0.5,
				0.5
			],
			"threshold": 0.6,
			"epoch": "best",
			"min_talk_len": 10,
			"random_baseline": {}
		},
		"totals": {
			"eval": {
				"selected": 2061,
				"relevant": 4361,
				"true_positives": 179,
				"false_positives": 1882,
				"false_negatives": 4182,
				"precision": 0.08685104318292092,
				"recall": 0.0410456317358404,
				"f1_score": 0.05574587355963874
			},
			"valid": {
				"selected": 1821,
				"relevant": 3804,
				"true_positives": 176,
				"false_positives": 1645,
				"false_negatives": 3628,
				"precision": 0.09665019220208676,
				"recall": 0.046267087276550996,
				"f1_score": 0.06257777777777777
			}
		}
	},
	{
		"config": {
			"margin_of_error": [
				-0.5,
				0.5
			],
			"threshold": 0.65,
			"epoch": "best",
			"min_talk_len": null,
			"random_baseline": {}
		},
		"totals": {
			"eval": {
				"selected": 5778,
				"relevant": 5778,
				"true_positives": 268,
				"false_positives": 5510,
				"false_negatives": 5510,
				"precision": 0.0463828314295604,
				"recall": 0.0463828314295604,
				"f1_score": 0.0463828314295604
			},
			"valid": {
				"selected": 5048,
				"relevant": 5048,
				"true_positives": 237,
				"false_positives": 4811,
				"false_negatives": 4811,
				"precision": 0.04694928684627575,
				"recall": 0.04694928684627575,
				"f1_score": 0.04694928684627575
			}
		}
	},
	{
		"config": {
			"margin_of_error": [
				-0.5,
				0.5
			],
			"threshold": 0.65,
			"epoch": "best",
			"min_talk_len": 0,
			"random_baseline": {}
		},
		"totals": {
			"eval": {
				"selected": 2796,
				"relevant": 5557,
				"true_positives": 261,
				"false_positives": 2535,
				"false_negatives": 5296,
				"precision": 0.09334763948497854,
				"recall": 0.046967788375022496,
				"f1_score": 0.06249251765832635
			},
			"valid": {
				"selected": 2267,
				"relevant": 4865,
				"true_positives": 197,
				"false_positives": 2070,
				"false_negatives": 4668,
				"precision": 0.08689898544331716,
				"recall": 0.04049331963001028,
				"f1_score": 0.055243970835670224
			}
		}
	},
	{
		"config": {
			"margin_of_error": [
				-0.5,
				0.5
			],
			"threshold": 0.65,
			"epoch": "best",
			"min_talk_len": 5,
			"random_baseline": {}
		},
		"totals": {
			"eval": {
				"selected": 2438,
				"relevant": 5192,
				"true_positives": 230,
				"false_positives": 2208,
				"false_negatives": 4962,
				"precision": 0.09433962264150944,
				"recall": 0.04429892141756549,
				"f1_score": 0.06028833551769332
			},
			"valid": {
				"selected": 2070,
				"relevant": 4567,
				"true_positives": 210,
				"false_positives": 1860,
				"false_negatives": 4357,
				"precision": 0.10144927536231885,
				"recall": 0.04598204510619663,
				"f1_score": 0.06328160313394605
			}
		}
	},
	{
		"config": {
			"margin_of_error": [
				-0.5,
				0.5
			],
			"threshold": 0.65,
			"epoch": "best",
			"min_talk_len": 10,
			"random_baseline": {}
		},
		"totals": {
			"eval": {
				"selected": 2072,
				"relevant": 4361,
				"true_positives": 209,
				"false_positives": 1863,
				"false_negatives": 4152,
				"precision": 0.10086872586872588,
				"recall": 0.047924787892685165,
				"f1_score": 0.06497745997201929
			},
			"valid": {
				"selected": 1776,
				"relevant": 3804,
				"true_positives": 168,
				"false_positives": 1608,
				"false_negatives": 3636,
				"precision": 0.0945945945945946,
				"recall": 0.04416403785488959,
				"f1_score": 0.060215053763440864
			}
		}
	},
	{
		"config": {
			"margin_of_error": [
				-0.5,
				0.5
			],
			"threshold": 0.7,
			"epoch": "best",
			"min_talk_len": null,
			"random_baseline": {}
		},
		"totals": {
			"eval": {
				"selected": 5778,
				"relevant": 5778,
				"true_positives": 248,
				"false_positives": 5530,
				"false_negatives": 5530,
				"precision": 0.04292142609899619,
				"recall": 0.04292142609899619,
				"f1_score": 0.04292142609899619
			},
			"valid": {
				"selected": 5048,
				"relevant": 5048,
				"true_positives": 218,
				"false_positives": 4830,
				"false_negatives": 4830,
				"precision": 0.04318541996830428,
				"recall": 0.04318541996830428,
				"f1_score": 0.04318541996830428
			}
		}
	},
	{
		"config": {
			"margin_of_error": [
				-0.5,
				0.5
			],
			"threshold": 0.7,
			"epoch": "best",
			"min_talk_len": 0,
			"random_baseline": {}
		},
		"totals": {
			"eval": {
				"selected": 2645,
				"relevant": 5557,
				"true_positives": 248,
				"false_positives": 2397,
				"false_negatives": 5309,
				"precision": 0.09376181474480151,
				"recall": 0.04462839661687961,
				"f1_score": 0.06047305535235309
			},
			"valid": {
				"selected": 2322,
				"relevant": 4865,
				"true_positives": 221,
				"false_positives": 2101,
				"false_negatives": 4644,
				"precision": 0.09517657192075797,
				"recall": 0.04542651593011305,
				"f1_score": 0.06149993042994295
			}
		}
	},
	{
		"config": {
			"margin_of_error": [
				-0.5,
				0.5
			],
			"threshold": 0.7,
			"epoch": "best",
			"min_talk_len": 5,
			"random_baseline": {}
		},
		"totals": {
			"eval": {
				"selected": 2440,
				"relevant": 5192,
				"true_positives": 231,
				"false_positives": 2209,
				"false_negatives": 4961,
				"precision": 0.09467213114754099,
				"recall": 0.04449152542372881,
				"f1_score": 0.060534591194968554
			},
			"valid": {
				"selected": 2187,
				"relevant": 4567,
				"true_positives": 208,
				"false_positives": 1979,
				"false_negatives": 4359,
				"precision": 0.09510745313214448,
				"recall": 0.04554412086708999,
				"f1_score": 0.06159312999703879
			}
		}
	},
	{
		"config": {
			"margin_of_error": [
				-0.5,
				0.5
			],
			"threshold": 0.7,
			"epoch": "best",
			"min_talk_len": 10,
			"random_baseline": {}
		},
		"totals": {
			"eval": {
				"selected": 2002,
				"relevant": 4361,
				"true_positives": 194,
				"false_positives": 1808,
				"false_negatives": 4167,
				"precision": 0.0969030969030969,
				"recall": 0.04448520981426279,
				"f1_score": 0.06097752632406098
			},
			"valid": {
				"selected": 1766,
				"relevant": 3804,
				"true_positives": 180,
				"false_positives": 1586,
				"false_negatives": 3624,
				"precision": 0.10192525481313704,
				"recall": 0.0473186119873817,
				"f1_score": 0.06463195691202872
			}
		}
	},
	{
		"config": {
			"margin_of_error": [
				0,
				1
			],
			"threshold": 0.5,
			"epoch": "best",
			"min_talk_len": null,
			"random_baseline": {}
		},
		"totals": {
			"eval": {
				"selected": 5778,
				"relevant": 5778,
				"true_positives": 261,
				"false_positives": 5517,
				"false_negatives": 5517,
				"precision": 0.045171339563862926,
				"recall": 0.045171339563862926,
				"f1_score": 0.04517133956386293
			},
			"valid": {
				"selected": 5048,
				"relevant": 5048,
				"true_positives": 225,
				"false_positives": 4823,
				"false_negatives": 4823,
				"precision": 0.04457210776545167,
				"recall": 0.04457210776545167,
				"f1_score": 0.04457210776545167
			}
		}
	},
	{
		"config": {
			"margin_of_error": [
				0,
				1
			],
			"threshold": 0.5,
			"epoch": "best",
			"min_talk_len": 0,
			"random_baseline": {}
		},
		"totals": {
			"eval": {
				"selected": 2792,
				"relevant": 5557,
				"true_positives": 245,
				"false_positives": 2547,
				"false_negatives": 5312,
				"precision": 0.08775071633237823,
				"recall": 0.0440885369803851,
				"f1_score": 0.05868966343274643
			},
			"valid": {
				"selected": 2301,
				"relevant": 4865,
				"true_positives": 189,
				"false_positives": 2112,
				"false_negatives": 4676,
				"precision": 0.08213820078226858,
				"recall": 0.03884892086330935,
				"f1_score": 0.05274909293887803
			}
		}
	},
	{
		"config": {
			"margin_of_error": [
				0,
				1
			],
			"threshold": 0.5,
			"epoch": "best",
			"min_talk_len": 5,
			"random_baseline": {}
		},
		"totals": {
			"eval": {
				"selected": 2467,
				"relevant": 5192,
				"true_positives": 219,
				"false_positives": 2248,
				"false_negatives": 4973,
				"precision": 0.08877178759627077,
				"recall": 0.042180277349768876,
				"f1_score": 0.05718762240501371
			},
			"valid": {
				"selected": 2133,
				"relevant": 4567,
				"true_positives": 194,
				"false_positives": 1939,
				"false_negatives": 4373,
				"precision": 0.09095171120487576,
				"recall": 0.04247865119334355,
				"f1_score": 0.05791044776119402
			}
		}
	},
	{
		"config": {
			"margin_of_error": [
				0,
				1
			],
			"threshold": 0.5,
			"epoch": "best",
			"min_talk_len": 10,
			"random_baseline": {}
		},
		"totals": {
			"eval": {
				"selected": 2148,
				"relevant": 4361,
				"true_positives": 178,
				"false_positives": 1970,
				"false_negatives": 4183,
				"precision": 0.08286778398510242,
				"recall": 0.04081632653061224,
				"f1_score": 0.054693501305884164
			},
			"valid": {
				"selected": 1757,
				"relevant": 3804,
				"true_positives": 172,
				"false_positives": 1585,
				"false_negatives": 3632,
				"precision": 0.09789413773477519,
				"recall": 0.0452155625657203,
				"f1_score": 0.061859377809746444
			}
		}
	},
	{
		"config": {
			"margin_of_error": [
				0,
				1
			],
			"threshold": 0.6,
			"epoch": "best",
			"min_talk_len": null,
			"random_baseline": {}
		},
		"totals": {
			"eval": {
				"selected": 5778,
				"relevant": 5778,
				"true_positives": 255,
				"false_positives": 5523,
				"false_negatives": 5523,
				"precision": 0.044132917964693666,
				"recall": 0.044132917964693666,
				"f1_score": 0.044132917964693666
			},
			"valid": {
				"selected": 5048,
				"relevant": 5048,
				"true_positives": 221,
				"false_positives": 4827,
				"false_negatives": 4827,
				"precision": 0.0437797147385103,
				"recall": 0.0437797147385103,
				"f1_score": 0.0437797147385103
			}
		}
	},
	{
		"config": {
			"margin_of_error": [
				0,
				1
			],
			"threshold": 0.6,
			"epoch": "best",
			"min_talk_len": 0,
			"random_baseline": {}
		},
		"totals": {
			"eval": {
				"selected": 2752,
				"relevant": 5557,
				"true_positives": 243,
				"false_positives": 2509,
				"false_negatives": 5314,
				"precision": 0.08829941860465117,
				"recall": 0.04372863055605543,
				"f1_score": 0.05849079311589842
			},
			"valid": {
				"selected": 2347,
				"relevant": 4865,
				"true_positives": 220,
				"false_positives": 2127,
				"false_negatives": 4645,
				"precision": 0.09373668512995313,
				"recall": 0.045220966084275435,
				"f1_score": 0.061009428729894614
			}
		}
	},
	{
		"config": {
			"margin_of_error": [
				0,
				1
			],
			"threshold": 0.6,
			"epoch": "best",
			"min_talk_len": 5,
			"random_baseline": {}
		},
		"totals": {
			"eval": {
				"selected": 2568,
				"relevant": 5192,
				"true_positives": 220,
				"false_positives": 2348,
				"false_negatives": 4972,
				"precision": 0.08566978193146417,
				"recall": 0.0423728813559322,
				"f1_score": 0.056701030927835044
			},
			"valid": {
				"selected": 2155,
				"relevant": 4567,
				"true_positives": 208,
				"false_positives": 1947,
				"false_negatives": 4359,
				"precision": 0.09651972157772622,
				"recall": 0.04554412086708999,
				"f1_score": 0.06188634335019339
			}
		}
	},
	{
		"config": {
			"margin_of_error": [
				0,
				1
			],
			"threshold": 0.6,
			"epoch": "best",
			"min_talk_len": 10,
			"random_baseline": {}
		},
		"totals": {
			"eval": {
				"selected": 2103,
				"relevant": 4361,
				"true_positives": 193,
				"false_positives": 1910,
				"false_negatives": 4168,
				"precision": 0.091773656680932,
				"recall": 0.04425590460903463,
				"f1_score": 0.05971534653465347
			},
			"valid": {
				"selected": 1798,
				"relevant": 3804,
				"true_positives": 175,
				"false_positives": 1623,
				"false_negatives": 3629,
				"precision": 0.09733036707452725,
				"recall": 0.04600420609884332,
				"f1_score": 0.06247768654052124
			}
		}
	},
	{
		"config": {
			"margin_of_error": [
				0,
				1
			],
			"threshold": 0.65,
			"epoch": "best",
			"min_talk_len": null,
			"random_baseline": {}
		},
		"totals": {
			"eval": {
				"selected": 5778,
				"relevant": 5778,
				"true_positives": 246,
				"false_positives": 5532,
				"false_negatives": 5532,
				"precision": 0.04257528556593977,
				"recall": 0.04257528556593977,
				"f1_score": 0.04257528556593977
			},
			"valid": {
				"selected": 5048,
				"relevant": 5048,
				"true_positives": 236,
				"false_positives": 4812,
				"false_negatives": 4812,
				"precision": 0.04675118858954041,
				"recall": 0.04675118858954041,
				"f1_score": 0.04675118858954041
			}
		}
	},
	{
		"config": {
			"margin_of_error": [
				0,
				1
			],
			"threshold": 0.65,
			"epoch": "best",
			"min_talk_len": 0,
			"random_baseline": {}
		},
		"totals": {
			"eval": {
				"selected": 2773,
				"relevant": 5557,
				"true_positives": 249,
				"false_positives": 2524,
				"false_negatives": 5308,
				"precision": 0.08979444644789038,
				"recall": 0.04480834982904445,
				"f1_score": 0.059783913565426165
			},
			"valid": {
				"selected": 2374,
				"relevant": 4865,
				"true_positives": 232,
				"false_positives": 2142,
				"false_negatives": 4633,
				"precision": 0.09772535804549284,
				"recall": 0.047687564234326824,
				"f1_score": 0.06409725100151956
			}
		}
	},
	{
		"config": {
			"margin_of_error": [
				0,
				1
			],
			"threshold": 0.65,
			"epoch": "best",
			"min_talk_len": 5,
			"random_baseline": {}
		},
		"totals": {
			"eval": {
				"selected": 2447,
				"relevant": 5192,
				"true_positives": 221,
				"false_positives": 2226,
				"false_negatives": 4971,
				"precision": 0.09031467102574581,
				"recall": 0.042565485362095534,
				"f1_score": 0.05786097656761356
			},
			"valid": {
				"selected": 2142,
				"relevant": 4567,
				"true_positives": 220,
				"false_positives": 1922,
				"false_negatives": 4347,
				"precision": 0.10270774976657329,
				"recall": 0.0481716663017298,
				"f1_score": 0.06558354449247279
			}
		}
	},
	{
		"config": {
			"margin_of_error": [
				0,
				1
			],
			"threshold": 0.65,
			"epoch": "best",
			"min_talk_len": 10,
			"random_baseline": {}
		},
		"totals": {
			"eval": {
				"selected": 2053,
				"relevant": 4361,
				"true_positives": 177,
				"false_positives": 1876,
				"false_negatives": 4184,
				"precision": 0.08621529469069654,
				"recall": 0.04058702132538409,
				"f1_score": 0.05519176800748363
			},
			"valid": {
				"selected": 1749,
				"relevant": 3804,
				"true_positives": 176,
				"false_positives": 1573,
				"false_negatives": 3628,
				"precision": 0.10062893081761007,
				"recall": 0.046267087276550996,
				"f1_score": 0.06338915901314605
			}
		}
	},
	{
		"config": {
			"margin_of_error": [
				0,
				1
			],
			"threshold": 0.7,
			"epoch": "best",
			"min_talk_len": null,
			"random_baseline": {}
		},
		"totals": {
			"eval": {
				"selected": 5778,
				"relevant": 5778,
				"true_positives": 274,
				"false_positives": 5504,
				"false_negatives": 5504,
				"precision": 0.04742125302872966,
				"recall": 0.04742125302872966,
				"f1_score": 0.047421253028729654
			},
			"valid": {
				"selected": 5048,
				"relevant": 5048,
				"true_positives": 217,
				"false_positives": 4831,
				"false_negatives": 4831,
				"precision": 0.04298732171156894,
				"recall": 0.04298732171156894,
				"f1_score": 0.04298732171156894
			}
		}
	},
	{
		"config": {
			"margin_of_error": [
				0,
				1
			],
			"threshold": 0.7,
			"epoch": "best",
			"min_talk_len": 0,
			"random_baseline": {}
		},
		"totals": {
			"eval": {
				"selected": 2760,
				"relevant": 5557,
				"true_positives": 236,
				"false_positives": 2524,
				"false_negatives": 5321,
				"precision": 0.08550724637681159,
				"recall": 0.042468958070901563,
				"f1_score": 0.056751232415534446
			},
			"valid": {
				"selected": 2357,
				"relevant": 4865,
				"true_positives": 224,
				"false_positives": 2133,
				"false_negatives": 4641,
				"precision": 0.09503606279168435,
				"recall": 0.0460431654676259,
				"f1_score": 0.06203267792855165
			}
		}
	},
	{
		"config": {
			"margin_of_error": [
				0,
				1
			],
			"threshold": 0.7,
			"epoch": "best",
			"min_talk_len": 5,
			"random_baseline": {}
		},
		"totals": {
			"eval": {
				"selected": 2481,
				"relevant": 5192,
				"true_positives": 237,
				"false_positives": 2244,
				"false_negatives": 4955,
				"precision": 0.09552599758162031,
				"recall": 0.04564714946070878,
				"f1_score": 0.06177505538902646
			},
			"valid": {
				"selected": 2119,
				"relevant": 4567,
				"true_positives": 197,
				"false_positives": 1922,
				"false_negatives": 4370,
				"precision": 0.09296838131193959,
				"recall": 0.0431355375520035,
				"f1_score": 0.05892910559377804
			}
		}
	},
	{
		"config": {
			"margin_of_error": [
				0,
				1
			],
			"threshold": 0.7,
			"epoch": "best",
			"min_talk_len": 10,
			"random_baseline": {}
		},
		"totals": {
			"eval": {
				"selected": 2099,
				"relevant": 4361,
				"true_positives": 174,
				"false_positives": 1925,
				"false_negatives": 4187,
				"precision": 0.08289661743687471,
				"recall": 0.03989910570969961,
				"f1_score": 0.05386996904024768
			},
			"valid": {
				"selected": 1796,
				"relevant": 3804,
				"true_positives": 183,
				"false_positives": 1613,
				"false_negatives": 3621,
				"precision": 0.10189309576837416,
				"recall": 0.04810725552050473,
				"f1_score": 0.06535714285714285
			}
		}
	},
	{
		"config": {
			"margin_of_error": [
				-1,
				0
			],
			"threshold": 0.5,
			"epoch": "best",
			"min_talk_len": null,
			"random_baseline": {}
		},
		"totals": {
			"eval": {
				"selected": 5778,
				"relevant": 5778,
				"true_positives": 252,
				"false_positives": 5526,
				"false_negatives": 5526,
				"precision": 0.04361370716510903,
				"recall": 0.04361370716510903,
				"f1_score": 0.04361370716510903
			},
			"valid": {
				"selected": 5048,
				"relevant": 5048,
				"true_positives": 233,
				"false_positives": 4815,
				"false_negatives": 4815,
				"precision": 0.04615689381933439,
				"recall": 0.04615689381933439,
				"f1_score": 0.04615689381933439
			}
		}
	},
	{
		"config": {
			"margin_of_error": [
				-1,
				0
			],
			"threshold": 0.5,
			"epoch": "best",
			"min_talk_len": 0,
			"random_baseline": {}
		},
		"totals": {
			"eval": {
				"selected": 2741,
				"relevant": 5557,
				"true_positives": 269,
				"false_positives": 2472,
				"false_negatives": 5288,
				"precision": 0.09813936519518424,
				"recall": 0.04840741407234119,
				"f1_score": 0.0648348999758978
			},
			"valid": {
				"selected": 2319,
				"relevant": 4865,
				"true_positives": 178,
				"false_positives": 2141,
				"false_negatives": 4687,
				"precision": 0.07675722294092281,
				"recall": 0.03658787255909558,
				"f1_score": 0.04955456570155902
			}
		}
	},
	{
		"config": {
			"margin_of_error": [
				-1,
				0
			],
			"threshold": 0.5,
			"epoch": "best",
			"min_talk_len": 5,
			"random_baseline": {}
		},
		"totals": {
			"eval": {
				"selected": 2481,
				"relevant": 5192,
				"true_positives": 192,
				"false_positives": 2289,
				"false_negatives": 5000,
				"precision": 0.0773881499395405,
				"recall": 0.03697996918335902,
				"f1_score": 0.05004561449237587
			},
			"valid": {
				"selected": 2041,
				"relevant": 4567,
				"true_positives": 205,
				"false_positives": 1836,
				"false_negatives": 4362,
				"precision": 0.10044096031357178,
				"recall": 0.04488723450843004,
				"f1_score": 0.06204600484261501
			}
		}
	},
	{
		"config": {
			"margin_of_error": [
				-1,
				0
			],
			"threshold": 0.5,
			"epoch": "best",
			"min_talk_len": 10,
			"random_baseline": {}
		},
		"totals": {
			"eval": {
				"selected": 2081,
				"relevant": 4361,
				"true_positives": 166,
				"false_positives": 1915,
				"false_negatives": 4195,
				"precision": 0.07976934166266218,
				"recall": 0.03806466406787434,
				"f1_score": 0.05153678981682708
			},
			"valid": {
				"selected": 1805,
				"relevant": 3804,
				"true_positives": 187,
				"false_positives": 1618,
				"false_negatives": 3617,
				"precision": 0.10360110803324099,
				"recall": 0.049158780231335436,
				"f1_score": 0.06667855232661793
			}
		}
	},
	{
		"config": {
			"margin_of_error": [
				-1,
				0
			],
			"threshold": 0.6,
			"epoch": "best",
			"min_talk_len": null,
			"random_baseline": {}
		},
		"totals": {
			"eval": {
				"selected": 5778,
				"relevant": 5778,
				"true_positives": 263,
				"false_positives": 5515,
				"false_negatives": 5515,
				"precision": 0.04551748009691935,
				"recall": 0.04551748009691935,
				"f1_score": 0.04551748009691935
			},
			"valid": {
				"selected": 5048,
				"relevant": 5048,
				"true_positives": 240,
				"false_positives": 4808,
				"false_negatives": 4808,
				"precision": 0.04754358161648178,
				"recall": 0.04754358161648178,
				"f1_score": 0.04754358161648178
			}
		}
	},
	{
		"config": {
			"margin_of_error": [
				-1,
				0
			],
			"threshold": 0.6,
			"epoch": "best",
			"min_talk_len": 0,
			"random_baseline": {}
		},
		"totals": {
			"eval": {
				"selected": 2767,
				"relevant": 5557,
				"true_positives": 243,
				"false_positives": 2524,
				"false_negatives": 5314,
				"precision": 0.08782074448861583,
				"recall": 0.04372863055605543,
				"f1_score": 0.05838539163863527
			},
			"valid": {
				"selected": 2348,
				"relevant": 4865,
				"true_positives": 218,
				"false_positives": 2130,
				"false_negatives": 4647,
				"precision": 0.09284497444633731,
				"recall": 0.044809866392600206,
				"f1_score": 0.06044641619298489
			}
		}
	},
	{
		"config": {
			"margin_of_error": [
				-1,
				0
			],
			"threshold": 0.6,
			"epoch": "best",
			"min_talk_len": 5,
			"random_baseline": {}
		},
		"totals": {
			"eval": {
				"selected": 2462,
				"relevant": 5192,
				"true_positives": 240,
				"false_positives": 2222,
				"false_negatives": 4952,
				"precision": 0.09748172217709179,
				"recall": 0.046224961479198766,
				"f1_score": 0.06271230729030573
			},
			"valid": {
				"selected": 2171,
				"relevant": 4567,
				"true_positives": 206,
				"false_positives": 1965,
				"false_negatives": 4361,
				"precision": 0.09488714877936434,
				"recall": 0.04510619662798336,
				"f1_score": 0.061145740575838534
			}
		}
	},
	{
		"config": {
			"margin_of_error": [
				-1,
				0
			],
			"threshold": 0.6,
			"epoch": "best",
			"min_talk_len": 10,
			"random_baseline": {}
		},
		"totals": {
			"eval": {
				"selected": 2078,
				"relevant": 4361,
				"true_positives": 213,
				"false_positives": 1865,
				"false_negatives": 4148,
				"precision": 0.10250240615976901,
				"recall": 0.0488420087135978,
				"f1_score": 0.06615934151265725
			},
			"valid": {
				"selected": 1846,
				"relevant": 3804,
				"true_positives": 190,
				"false_positives": 1656,
				"false_negatives": 3614,
				"precision": 0.10292524377031419,
				"recall": 0.049947423764458466,
				"f1_score": 0.06725663716814159
			}
		}
	},
	{
		"config": {
			"margin_of_error": [
				-1,
				0
			],
			"threshold": 0.65,
			"epoch": "best",
			"min_talk_len": null,
			"random_baseline": {}
		},
		"totals": {
			"eval": {
				"selected": 5778,
				"relevant": 5778,
				"true_positives": 241,
				"false_positives": 5537,
				"false_negatives": 5537,
				"precision": 0.04170993423329872,
				"recall": 0.04170993423329872,
				"f1_score": 0.04170993423329872
			},
			"valid": {
				"selected": 5048,
				"relevant": 5048,
				"true_positives": 244,
				"false_positives": 4804,
				"false_negatives": 4804,
				"precision": 0.04833597464342314,
				"recall": 0.04833597464342314,
				"f1_score": 0.04833597464342314
			}
		}
	},
	{
		"config": {
			"margin_of_error": [
				-1,
				0
			],
			"threshold": 0.65,
			"epoch": "best",
			"min_talk_len": 0,
			"random_baseline": {}
		},
		"totals": {
			"eval": {
				"selected": 2787,
				"relevant": 5557,
				"true_positives": 230,
				"false_positives": 2557,
				"false_negatives": 5327,
				"precision": 0.08252601363473269,
				"recall": 0.04138923879791254,
				"f1_score": 0.0551294343240652
			},
			"valid": {
				"selected": 2373,
				"relevant": 4865,
				"true_positives": 204,
				"false_positives": 2169,
				"false_negatives": 4661,
				"precision": 0.08596713021491782,
				"recall": 0.04193216855087359,
				"f1_score": 0.05636916275214147
			}
		}
	},
	{
		"config": {
			"margin_of_error": [
				-1,
				0
			],
			"threshold": 0.65,
			"epoch": "best",
			"min_talk_len": 5,
			"random_baseline": {}
		},
		"totals": {
			"eval": {
				"selected": 2497,
				"relevant": 5192,
				"true_positives": 212,
				"false_positives": 2285,
				"false_negatives": 4980,
				"precision": 0.08490188225871045,
				"recall": 0.040832049306625574,
				"f1_score": 0.05514371179607231
			},
			"valid": {
				"selected": 2148,
				"relevant": 4567,
				"true_positives": 217,
				"false_positives": 1931,
				"false_negatives": 4350,
				"precision": 0.10102420856610801,
				"recall": 0.04751477994306985,
				"f1_score": 0.06463142218912882
			}
		}
	},
	{
		"config": {
			"margin_of_error": [
				-1,
				0
			],
			"threshold": 0.65,
			"epoch": "best",
			"min_talk_len": 10,
			"random_baseline": {}
		},
		"totals": {
			"eval": {
				"selected": 2054,
				"relevant": 4361,
				"true_positives": 227,
				"false_positives": 1827,
				"false_negatives": 4134,
				"precision": 0.11051606621226874,
				"recall": 0.052052281586792024,
				"f1_score": 0.07077162899454403
			},
			"valid": {
				"selected": 1772,
				"relevant": 3804,
				"true_positives": 189,
				"false_positives": 1583,
				"false_negatives": 3615,
				"precision": 0.10665914221218961,
				"recall": 0.04968454258675079,
				"f1_score": 0.06779053084648494
			}
		}
	},
	{
		"config": {
			"margin_of_error": [
				-1,
				0
			],
			"threshold": 0.7,
			"epoch": "best",
			"min_talk_len": null,
			"random_baseline": {}
		},
		"totals": {
			"eval": {
				"selected": 5778,
				"relevant": 5778,
				"true_positives": 275,
				"false_positives": 5503,
				"false_negatives": 5503,
				"precision": 0.047594323295257875,
				"recall": 0.047594323295257875,
				"f1_score": 0.04759432329525788
			},
			"valid": {
				"selected": 5048,
				"relevant": 5048,
				"true_positives": 232,
				"false_positives": 4816,
				"false_negatives": 4816,
				"precision": 0.04595879556259905,
				"recall": 0.04595879556259905,
				"f1_score": 0.045958795562599054
			}
		}
	},
	{
		"config": {
			"margin_of_error": [
				-1,
				0
			],
			"threshold": 0.7,
			"epoch": "best",
			"min_talk_len": 0,
			"random_baseline": {}
		},
		"totals": {
			"eval": {
				"selected": 2695,
				"relevant": 5557,
				"true_positives": 237,
				"false_positives": 2458,
				"false_negatives": 5320,
				"precision": 0.08794063079777366,
				"recall": 0.0426489112830664,
				"f1_score": 0.057440620455647115
			},
			"valid": {
				"selected": 2395,
				"relevant": 4865,
				"true_positives": 225,
				"false_positives": 2170,
				"false_negatives": 4640,
				"precision": 0.09394572025052192,
				"recall": 0.046248715313463515,
				"f1_score": 0.061983471074380174
			}
		}
	},
	{
		"config": {
			"margin_of_error": [
				-1,
				0
			],
			"threshold": 0.7,
			"epoch": "best",
			"min_talk_len": 5,
			"random_baseline": {}
		},
		"totals": {
			"eval": {
				"selected": 2396,
				"relevant": 5192,
				"true_positives": 226,
				"false_positives": 2170,
				"false_negatives": 4966,
				"precision": 0.09432387312186978,
				"recall": 0.04352850539291217,
				"f1_score": 0.05956773853452821
			},
			"valid": {
				"selected": 2141,
				"relevant": 4567,
				"true_positives": 224,
				"false_positives": 1917,
				"false_negatives": 4343,
				"precision": 0.10462400747314339,
				"recall": 0.04904751477994307,
				"f1_score": 0.06678592725104354
			}
		}
	},
	{
		"config": {
			"margin_of_error": [
				-1,
				0
			],
			"threshold": 0.7,
			"epoch": "best",
			"min_talk_len": 10,
			"random_baseline": {}
		},
		"totals": {
			"eval": {
				"selected": 2138,
				"relevant": 4361,
				"true_positives": 206,
				"false_positives": 1932,
				"false_negatives": 4155,
				"precision": 0.09635173058933583,
				"recall": 0.047236872277000685,
				"f1_score": 0.06339436836436374
			},
			"valid": {
				"selected": 1801,
				"relevant": 3804,
				"true_positives": 176,
				"false_positives": 1625,
				"false_negatives": 3628,
				"precision": 0.0977234869516935,
				"recall": 0.046267087276550996,
				"f1_score": 0.06280107047279215
			}
		}
	},
	{
		"config": {
			"margin_of_error": [
				-0.2,
				0.2
			],
			"threshold": 0.5,
			"epoch": "best",
			"min_talk_len": null,
			"random_baseline": {}
		},
		"totals": {
			"eval": {
				"selected": 5778,
				"relevant": 5778,
				"true_positives": 104,
				"false_positives": 5674,
				"false_negatives": 5674,
				"precision": 0.017999307718933887,
				"recall": 0.017999307718933887,
				"f1_score": 0.017999307718933887
			},
			"valid": {
				"selected": 5048,
				"relevant": 5048,
				"true_positives": 83,
				"false_positives": 4965,
				"false_negatives": 4965,
				"precision": 0.01644215530903328,
				"recall": 0.01644215530903328,
				"f1_score": 0.01644215530903328
			}
		}
	},
	{
		"config": {
			"margin_of_error": [
				-0.2,
				0.2
			],
			"threshold": 0.5,
			"epoch": "best",
			"min_talk_len": 0,
			"random_baseline": {}
		},
		"totals": {
			"eval": {
				"selected": 2705,
				"relevant": 5557,
				"true_positives": 107,
				"false_positives": 2598,
				"false_negatives": 5450,
				"precision": 0.03955637707948244,
				"recall": 0.019254993701637576,
				"f1_score": 0.02590171871217623
			},
			"valid": {
				"selected": 2371,
				"relevant": 4865,
				"true_positives": 97,
				"false_positives": 2274,
				"false_negatives": 4768,
				"precision": 0.04091100801349642,
				"recall": 0.019938335046248715,
				"f1_score": 0.026810392482034276
			}
		}
	},
	{
		"config": {
			"margin_of_error": [
				-0.2,
				0.2
			],
			"threshold": 0.5,
			"epoch": "best",
			"min_talk_len": 5,
			"random_baseline": {}
		},
		"totals": {
			"eval": {
				"selected": 2485,
				"relevant": 5192,
				"true_positives": 89,
				"false_positives": 2396,
				"false_negatives": 5103,
				"precision": 0.0358148893360161,
				"recall": 0.01714175654853621,
				"f1_score": 0.023186140419434675
			},
			"valid": {
				"selected": 2100,
				"relevant": 4567,
				"true_positives": 89,
				"false_positives": 2011,
				"false_negatives": 4478,
				"precision": 0.04238095238095238,
				"recall": 0.01948762864024524,
				"f1_score": 0.026698665066746664
			}
		}
	},
	{
		"config": {
			"margin_of_error": [
				-0.2,
				0.2
			],
			"threshold": 0.5,
			"epoch": "best",
			"min_talk_len": 10,
			"random_baseline": {}
		},
		"totals": {
			"eval": {
				"selected": 2105,
				"relevant": 4361,
				"true_positives": 84,
				"false_positives": 2021,
				"false_negatives": 4277,
				"precision": 0.039904988123515436,
				"recall": 0.019261637239165328,
				"f1_score": 0.025982060006186206
			},
			"valid": {
				"selected": 1777,
				"relevant": 3804,
				"true_positives": 74,
				"false_positives": 1703,
				"false_negatives": 3730,
				"precision": 0.04164321890827237,
				"recall": 0.019453207150368034,
				"f1_score": 0.026518545063608668
			}
		}
	},
	{
		"config": {
			"margin_of_error": [
				-0.2,
				0.2
			],
			"threshold": 0.6,
			"epoch": "best",
			"min_talk_len": null,
			"random_baseline": {}
		},
		"totals": {
			"eval": {
				"selected": 5778,
				"relevant": 5778,
				"true_positives": 100,
				"false_positives": 5678,
				"false_negatives": 5678,
				"precision": 0.017307026652821047,
				"recall": 0.017307026652821047,
				"f1_score": 0.017307026652821047
			},
			"valid": {
				"selected": 5048,
				"relevant": 5048,
				"true_positives": 92,
				"false_positives": 4956,
				"false_negatives": 4956,
				"precision": 0.018225039619651346,
				"recall": 0.018225039619651346,
				"f1_score": 0.018225039619651346
			}
		}
	},
	{
		"config": {
			"margin_of_error": [
				-0.2,
				0.2
			],
			"threshold": 0.6,
			"epoch": "best",
			"min_talk_len": 0,
			"random_baseline": {}
		},
		"totals": {
			"eval": {
				"selected": 2725,
				"relevant": 5557,
				"true_positives": 97,
				"false_positives": 2628,
				"false_negatives": 5460,
				"precision": 0.035596330275229356,
				"recall": 0.017455461579989204,
				"f1_score": 0.02342429364887708
			},
			"valid": {
				"selected": 2346,
				"relevant": 4865,
				"true_positives": 80,
				"false_positives": 2266,
				"false_negatives": 4785,
				"precision": 0.03410059676044331,
				"recall": 0.01644398766700925,
				"f1_score": 0.02218832339481348
			}
		}
	},
	{
		"config": {
			"margin_of_error": [
				-0.2,
				0.2
			],
			"threshold": 0.6,
			"epoch": "best",
			"min_talk_len": 5,
			"random_baseline": {}
		},
		"totals": {
			"eval": {
				"selected": 2539,
				"relevant": 5192,
				"true_positives": 93,
				"false_positives": 2446,
				"false_negatives": 5099,
				"precision": 0.03662859393461993,
				"recall": 0.01791217257318952,
				"f1_score": 0.02405898331393093
			},
			"valid": {
				"selected": 2104,
				"relevant": 4567,
				"true_positives": 78,
				"false_positives": 2026,
				"false_negatives": 4489,
				"precision": 0.0370722433460076,
				"recall": 0.017079045325158748,
				"f1_score": 0.02338479988007795
			}
		}
	},
	{
		"config": {
			"margin_of_error": [
				-0.2,
				0.2
			],
			"threshold": 0.6,
			"epoch": "best",
			"min_talk_len": 10,
			"random_baseline": {}
		},
		"totals": {
			"eval": {
				"selected": 2047,
				"relevant": 4361,
				"true_positives": 72,
				"false_positives": 1975,
				"false_negatives": 4289,
				"precision": 0.03517342452369321,
				"recall": 0.016509974776427426,
				"f1_score": 0.02247191011235955
			},
			"valid": {
				"selected": 1808,
				"relevant": 3804,
				"true_positives": 72,
				"false_positives": 1736,
				"false_negatives": 3732,
				"precision": 0.03982300884955752,
				"recall": 0.01892744479495268,
				"f1_score": 0.02565930149679259
			}
		}
	},
	{
		"config": {
			"margin_of_error": [
				-0.2,
				0.2
			],
			"threshold": 0.65,
			"epoch": "best",
			"min_talk_len": null,
			"random_baseline": {}
		},
		"totals": {
			"eval": {
				"selected": 5778,
				"relevant": 5778,
				"true_positives": 111,
				"false_positives": 5667,
				"false_negatives": 5667,
				"precision": 0.01921079958463136,
				"recall": 0.01921079958463136,
				"f1_score": 0.01921079958463136
			},
			"valid": {
				"selected": 5048,
				"relevant": 5048,
				"true_positives": 87,
				"false_positives": 4961,
				"false_negatives": 4961,
				"precision": 0.017234548335974643,
				"recall": 0.017234548335974643,
				"f1_score": 0.017234548335974643
			}
		}
	},
	{
		"config": {
			"margin_of_error": [
				-0.2,
				0.2
			],
			"threshold": 0.65,
			"epoch": "best",
			"min_talk_len": 0,
			"random_baseline": {}
		},
		"totals": {
			"eval": {
				"selected": 2622,
				"relevant": 5557,
				"true_positives": 94,
				"false_positives": 2528,
				"false_negatives": 5463,
				"precision": 0.03585049580472922,
				"recall": 0.01691560194349469,
				"f1_score": 0.02298569507274728
			},
			"valid": {
				"selected": 2376,
				"relevant": 4865,
				"true_positives": 100,
				"false_positives": 2276,
				"false_negatives": 4765,
				"precision": 0.04208754208754209,
				"recall": 0.020554984583761562,
				"f1_score": 0.027620494406849883
			}
		}
	},
	{
		"config": {
			"margin_of_error": [
				-0.2,
				0.2
			],
			"threshold": 0.65,
			"epoch": "best",
			"min_talk_len": 5,
			"random_baseline": {}
		},
		"totals": {
			"eval": {
				"selected": 2464,
				"relevant": 5192,
				"true_positives": 83,
				"false_positives": 2381,
				"false_negatives": 5109,
				"precision": 0.033685064935064936,
				"recall": 0.015986132511556242,
				"f1_score": 0.02168234064785789
			},
			"valid": {
				"selected": 2132,
				"relevant": 4567,
				"true_positives": 79,
				"false_positives": 2053,
				"false_negatives": 4488,
				"precision": 0.037054409005628515,
				"recall": 0.017298007444712066,
				"f1_score": 0.023585609792506346
			}
		}
	},
	{
		"config": {
			"margin_of_error": [
				-0.2,
				0.2
			],
			"threshold": 0.65,
			"epoch": "best",
			"min_talk_len": 10,
			"random_baseline": {}
		},
		"totals": {
			"eval": {
				"selected": 2063,
				"relevant": 4361,
				"true_positives": 91,
				"false_positives": 1972,
				"false_negatives": 4270,
				"precision": 0.04411051866214251,
				"recall": 0.02086677367576244,
				"f1_score": 0.02833125778331258
			},
			"valid": {
				"selected": 1779,
				"relevant": 3804,
				"true_positives": 75,
				"false_positives": 1704,
				"false_negatives": 3729,
				"precision": 0.04215851602023609,
				"recall": 0.01971608832807571,
				"f1_score": 0.026867275658248254
			}
		}
	},
	{
		"config": {
			"margin_of_error": [
				-0.2,
				0.2
			],
			"threshold": 0.7,
			"epoch": "best",
			"min_talk_len": null,
			"random_baseline": {}
		},
		"totals": {
			"eval": {
				"selected": 5778,
				"relevant": 5778,
				"true_positives": 95,
				"false_positives": 5683,
				"false_negatives": 5683,
				"precision": 0.016441675320179993,
				"recall": 0.016441675320179993,
				"f1_score": 0.016441675320179993
			},
			"valid": {
				"selected": 5048,
				"relevant": 5048,
				"true_positives": 121,
				"false_positives": 4927,
				"false_negatives": 4927,
				"precision": 0.023969889064976227,
				"recall": 0.023969889064976227,
				"f1_score": 0.023969889064976227
			}
		}
	},
	{
		"config": {
			"margin_of_error": [
				-0.2,
				0.2
			],
			"threshold": 0.7,
			"epoch": "best",
			"min_talk_len": 0,
			"random_baseline": {}
		},
		"totals": {
			"eval": {
				"selected": 2768,
				"relevant": 5557,
				"true_positives": 99,
				"false_positives": 2669,
				"false_negatives": 5458,
				"precision": 0.035765895953757225,
				"recall": 0.017815368004318877,
				"f1_score": 0.02378378378378378
			},
			"valid": {
				"selected": 2303,
				"relevant": 4865,
				"true_positives": 87,
				"false_positives": 2216,
				"false_negatives": 4778,
				"precision": 0.0377768128528007,
				"recall": 0.01788283658787256,
				"f1_score": 0.024274553571428572
			}
		}
	},
	{
		"config": {
			"margin_of_error": [
				-0.2,
				0.2
			],
			"threshold": 0.7,
			"epoch": "best",
			"min_talk_len": 5,
			"random_baseline": {}
		},
		"totals": {
			"eval": {
				"selected": 2468,
				"relevant": 5192,
				"true_positives": 86,
				"false_positives": 2382,
				"false_negatives": 5106,
				"precision": 0.03484602917341977,
				"recall": 0.016563944530046226,
				"f1_score": 0.02245430809399478
			},
			"valid": {
				"selected": 2122,
				"relevant": 4567,
				"true_positives": 81,
				"false_positives": 2041,
				"false_negatives": 4486,
				"precision": 0.03817153628652215,
				"recall": 0.0177359316838187,
				"f1_score": 0.02421886679623262
			}
		}
	},
	{
		"config": {
			"margin_of_error": [
				-0.2,
				0.2
			],
			"threshold": 0.7,
			"epoch": "best",
			"min_talk_len": 10,
			"random_baseline": {}
		},
		"totals": {
			"eval": {
				"selected": 2094,
				"relevant": 4361,
				"true_positives": 91,
				"false_positives": 2003,
				"false_negatives": 4270,
				"precision": 0.04345749761222541,
				"recall": 0.02086677367576244,
				"f1_score": 0.02819519752130132
			},
			"valid": {
				"selected": 1795,
				"relevant": 3804,
				"true_positives": 78,
				"false_positives": 1717,
				"false_negatives": 3726,
				"precision": 0.043454038997214485,
				"recall": 0.02050473186119874,
				"f1_score": 0.027862118235399178
			}
		}
	}
]