[
	{
		"config": {
			"margin_of_error": [
				-0.1,
				0.5
			],
			"threshold": 0.5,
			"epoch": "11",
			"min_talk_len": null,
			"weights_file": "epoch-011.pkl"
		},
		"totals": {
			"eval": {
				"selected": 37668,
				"relevant": 5778,
				"true_positives": 2083,
				"false_positives": 35585,
				"false_negatives": 3695,
				"precision": 0.05529892747159393,
				"recall": 0.36050536517826237,
				"f1_score": 0.09588914974911385
			},
			"valid": {
				"selected": 30980,
				"relevant": 5048,
				"true_positives": 1755,
				"false_positives": 29225,
				"false_negatives": 3293,
				"precision": 0.056649451258876694,
				"recall": 0.347662440570523,
				"f1_score": 0.09742422560230932
			}
		}
	},
	{
		"config": {
			"margin_of_error": [
				-0.1,
				0.5
			],
			"threshold": 0.5,
			"epoch": "11",
			"min_talk_len": 5,
			"weights_file": "epoch-011.pkl"
		},
		"totals": {
			"eval": {
				"selected": 18247,
				"relevant": 5192,
				"true_positives": 1930,
				"false_positives": 16317,
				"false_negatives": 3262,
				"precision": 0.10577081164026964,
				"recall": 0.3717257318952234,
				"f1_score": 0.16468279363454072
			},
			"valid": {
				"selected": 15285,
				"relevant": 4567,
				"true_positives": 1632,
				"false_positives": 13653,
				"false_negatives": 2935,
				"precision": 0.10677134445534837,
				"recall": 0.3573461791110138,
				"f1_score": 0.16441668345758612
			}
		}
	},
	{
		"config": {
			"margin_of_error": [
				-0.1,
				0.5
			],
			"threshold": 0.5,
			"epoch": "11",
			"min_talk_len": 10,
			"weights_file": "epoch-011.pkl"
		},
		"totals": {
			"eval": {
				"selected": 15534,
				"relevant": 4361,
				"true_positives": 1614,
				"false_positives": 13920,
				"false_negatives": 2747,
				"precision": 0.10390112012359985,
				"recall": 0.3700986012382481,
				"f1_score": 0.1622518220658457
			},
			"valid": {
				"selected": 12776,
				"relevant": 3804,
				"true_positives": 1356,
				"false_positives": 11420,
				"false_negatives": 2448,
				"precision": 0.10613650594865373,
				"recall": 0.35646687697160884,
				"f1_score": 0.1635705669481303
			}
		}
	},
	{
		"config": {
			"margin_of_error": [
				-0.1,
				0.5
			],
			"threshold": 0.6,
			"epoch": "11",
			"min_talk_len": null,
			"weights_file": "epoch-011.pkl"
		},
		"totals": {
			"eval": {
				"selected": 12589,
				"relevant": 5778,
				"true_positives": 1015,
				"false_positives": 11574,
				"false_negatives": 4763,
				"precision": 0.08062594328381921,
				"recall": 0.17566632052613362,
				"f1_score": 0.1105243099036315
			},
			"valid": {
				"selected": 10359,
				"relevant": 5048,
				"true_positives": 838,
				"false_positives": 9521,
				"false_negatives": 4210,
				"precision": 0.08089583936673424,
				"recall": 0.16600633914421553,
				"f1_score": 0.10878172259362628
			}
		}
	},
	{
		"config": {
			"margin_of_error": [
				-0.1,
				0.5
			],
			"threshold": 0.6,
			"epoch": "11",
			"min_talk_len": 5,
			"weights_file": "epoch-011.pkl"
		},
		"totals": {
			"eval": {
				"selected": 5841,
				"relevant": 5192,
				"true_positives": 948,
				"false_positives": 4893,
				"false_negatives": 4244,
				"precision": 0.1623009758602979,
				"recall": 0.18258859784283513,
				"f1_score": 0.17184809208737425
			},
			"valid": {
				"selected": 4767,
				"relevant": 4567,
				"true_positives": 776,
				"false_positives": 3991,
				"false_negatives": 3791,
				"precision": 0.16278581917348436,
				"recall": 0.1699146047733742,
				"f1_score": 0.16627383758302977
			}
		}
	},
	{
		"config": {
			"margin_of_error": [
				-0.1,
				0.5
			],
			"threshold": 0.6,
			"epoch": "11",
			"min_talk_len": 10,
			"weights_file": "epoch-011.pkl"
		},
		"totals": {
			"eval": {
				"selected": 4963,
				"relevant": 4361,
				"true_positives": 804,
				"false_positives": 4159,
				"false_negatives": 3557,
				"precision": 0.1619987910537981,
				"recall": 0.18436138500343957,
				"f1_score": 0.17245817245817247
			},
			"valid": {
				"selected": 4022,
				"relevant": 3804,
				"true_positives": 648,
				"false_positives": 3374,
				"false_negatives": 3156,
				"precision": 0.16111387369467928,
				"recall": 0.17034700315457413,
				"f1_score": 0.16560184002044467
			}
		}
	},
	{
		"config": {
			"margin_of_error": [
				-0.1,
				0.5
			],
			"threshold": 0.65,
			"epoch": "11",
			"min_talk_len": null,
			"weights_file": "epoch-011.pkl"
		},
		"totals": {
			"eval": {
				"selected": 4321,
				"relevant": 5778,
				"true_positives": 446,
				"false_positives": 3875,
				"false_negatives": 5332,
				"precision": 0.10321684795186299,
				"recall": 0.07718933887158186,
				"f1_score": 0.08832557678978117
			},
			"valid": {
				"selected": 3648,
				"relevant": 5048,
				"true_positives": 376,
				"false_positives": 3272,
				"false_negatives": 4672,
				"precision": 0.10307017543859649,
				"recall": 0.07448494453248812,
				"f1_score": 0.08647654093836246
			}
		}
	},
	{
		"config": {
			"margin_of_error": [
				-0.1,
				0.5
			],
			"threshold": 0.65,
			"epoch": "11",
			"min_talk_len": 5,
			"weights_file": "epoch-011.pkl"
		},
		"totals": {
			"eval": {
				"selected": 2083,
				"relevant": 5192,
				"true_positives": 417,
				"false_positives": 1666,
				"false_negatives": 4775,
				"precision": 0.20019203072491598,
				"recall": 0.08031587057010786,
				"f1_score": 0.11463917525773197
			},
			"valid": {
				"selected": 1724,
				"relevant": 4567,
				"true_positives": 351,
				"false_positives": 1373,
				"false_negatives": 4216,
				"precision": 0.20359628770301624,
				"recall": 0.07685570396321437,
				"f1_score": 0.11158798283261805
			}
		}
	},
	{
		"config": {
			"margin_of_error": [
				-0.1,
				0.5
			],
			"threshold": 0.65,
			"epoch": "11",
			"min_talk_len": 10,
			"weights_file": "epoch-011.pkl"
		},
		"totals": {
			"eval": {
				"selected": 1776,
				"relevant": 4361,
				"true_positives": 351,
				"false_positives": 1425,
				"false_negatives": 4010,
				"precision": 0.19763513513513514,
				"recall": 0.08048612703508369,
				"f1_score": 0.11438813752647874
			},
			"valid": {
				"selected": 1437,
				"relevant": 3804,
				"true_positives": 297,
				"false_positives": 1140,
				"false_negatives": 3507,
				"precision": 0.20668058455114824,
				"recall": 0.07807570977917981,
				"f1_score": 0.11333714939896966
			}
		}
	},
	{
		"config": {
			"margin_of_error": [
				-0.1,
				0.5
			],
			"threshold": 0.7,
			"epoch": "11",
			"min_talk_len": null,
			"weights_file": "epoch-011.pkl"
		},
		"totals": {
			"eval": {
				"selected": 920,
				"relevant": 5778,
				"true_positives": 109,
				"false_positives": 811,
				"false_negatives": 5669,
				"precision": 0.11847826086956521,
				"recall": 0.01886465905157494,
				"f1_score": 0.032547028963869816
			},
			"valid": {
				"selected": 789,
				"relevant": 5048,
				"true_positives": 102,
				"false_positives": 687,
				"false_negatives": 4946,
				"precision": 0.12927756653992395,
				"recall": 0.020206022187004756,
				"f1_score": 0.03494946033921535
			}
		}
	},
	{
		"config": {
			"margin_of_error": [
				-0.1,
				0.5
			],
			"threshold": 0.7,
			"epoch": "11",
			"min_talk_len": 5,
			"weights_file": "epoch-011.pkl"
		},
		"totals": {
			"eval": {
				"selected": 479,
				"relevant": 5192,
				"true_positives": 106,
				"false_positives": 373,
				"false_negatives": 5086,
				"precision": 0.22129436325678498,
				"recall": 0.020416024653312787,
				"f1_score": 0.037383177570093455
			},
			"valid": {
				"selected": 417,
				"relevant": 4567,
				"true_positives": 94,
				"false_positives": 323,
				"false_negatives": 4473,
				"precision": 0.22541966426858512,
				"recall": 0.020582439238011823,
				"f1_score": 0.03772070626003211
			}
		}
	},
	{
		"config": {
			"margin_of_error": [
				-0.1,
				0.5
			],
			"threshold": 0.7,
			"epoch": "11",
			"min_talk_len": 10,
			"weights_file": "epoch-011.pkl"
		},
		"totals": {
			"eval": {
				"selected": 417,
				"relevant": 4361,
				"true_positives": 88,
				"false_positives": 329,
				"false_negatives": 4273,
				"precision": 0.21103117505995203,
				"recall": 0.020178858060077964,
				"f1_score": 0.036835496023440766
			},
			"valid": {
				"selected": 360,
				"relevant": 3804,
				"true_positives": 80,
				"false_positives": 280,
				"false_negatives": 3724,
				"precision": 0.2222222222222222,
				"recall": 0.02103049421661409,
				"f1_score": 0.03842459173871277
			}
		}
	},
	{
		"config": {
			"margin_of_error": [
				-0.5,
				0.5
			],
			"threshold": 0.5,
			"epoch": "11",
			"min_talk_len": null,
			"weights_file": "epoch-011.pkl"
		},
		"totals": {
			"eval": {
				"selected": 37668,
				"relevant": 5778,
				"true_positives": 3521,
				"false_positives": 34147,
				"false_negatives": 2257,
				"precision": 0.09347456727195498,
				"recall": 0.609380408445829,
				"f1_score": 0.16208626801086407
			},
			"valid": {
				"selected": 30980,
				"relevant": 5048,
				"true_positives": 3098,
				"false_positives": 27882,
				"false_negatives": 1950,
				"precision": 0.1,
				"recall": 0.6137083993660856,
				"f1_score": 0.1719773509492617
			}
		}
	},
	{
		"config": {
			"margin_of_error": [
				-0.5,
				0.5
			],
			"threshold": 0.5,
			"epoch": "11",
			"min_talk_len": 5,
			"weights_file": "epoch-011.pkl"
		},
		"totals": {
			"eval": {
				"selected": 18223,
				"relevant": 5192,
				"true_positives": 3243,
				"false_positives": 14980,
				"false_negatives": 1949,
				"precision": 0.17796191625967184,
				"recall": 0.6246147919876733,
				"f1_score": 0.2770019218449712
			},
			"valid": {
				"selected": 15268,
				"relevant": 4567,
				"true_positives": 2861,
				"false_positives": 12407,
				"false_negatives": 1706,
				"precision": 0.18738538118941578,
				"recall": 0.6264506240420408,
				"f1_score": 0.2884799596672548
			}
		}
	},
	{
		"config": {
			"margin_of_error": [
				-0.5,
				0.5
			],
			"threshold": 0.5,
			"epoch": "11",
			"min_talk_len": 10,
			"weights_file": "epoch-011.pkl"
		},
		"totals": {
			"eval": {
				"selected": 15520,
				"relevant": 4361,
				"true_positives": 2737,
				"false_positives": 12783,
				"false_negatives": 1624,
				"precision": 0.17635309278350517,
				"recall": 0.6276083467094703,
				"f1_score": 0.27533826266284395
			},
			"valid": {
				"selected": 12767,
				"relevant": 3804,
				"true_positives": 2405,
				"false_positives": 10362,
				"false_negatives": 1399,
				"precision": 0.18837628260358738,
				"recall": 0.632229232386961,
				"f1_score": 0.29026612757226483
			}
		}
	},
	{
		"config": {
			"margin_of_error": [
				-0.5,
				0.5
			],
			"threshold": 0.6,
			"epoch": "11",
			"min_talk_len": null,
			"weights_file": "epoch-011.pkl"
		},
		"totals": {
			"eval": {
				"selected": 12589,
				"relevant": 5778,
				"true_positives": 1702,
				"false_positives": 10887,
				"false_negatives": 4076,
				"precision": 0.13519739455079832,
				"recall": 0.2945655936310142,
				"f1_score": 0.1853323896118038
			},
			"valid": {
				"selected": 10359,
				"relevant": 5048,
				"true_positives": 1425,
				"false_positives": 8934,
				"false_negatives": 3623,
				"precision": 0.13756154068925572,
				"recall": 0.28229001584786056,
				"f1_score": 0.18498085285909005
			}
		}
	},
	{
		"config": {
			"margin_of_error": [
				-0.5,
				0.5
			],
			"threshold": 0.6,
			"epoch": "11",
			"min_talk_len": 5,
			"weights_file": "epoch-011.pkl"
		},
		"totals": {
			"eval": {
				"selected": 5825,
				"relevant": 5192,
				"true_positives": 1578,
				"false_positives": 4247,
				"false_negatives": 3614,
				"precision": 0.27090128755364806,
				"recall": 0.3039291217257319,
				"f1_score": 0.2864663701552147
			},
			"valid": {
				"selected": 4757,
				"relevant": 4567,
				"true_positives": 1309,
				"false_positives": 3448,
				"false_negatives": 3258,
				"precision": 0.2751734286314904,
				"recall": 0.2866214144952923,
				"f1_score": 0.2807807807807808
			}
		}
	},
	{
		"config": {
			"margin_of_error": [
				-0.5,
				0.5
			],
			"threshold": 0.6,
			"epoch": "11",
			"min_talk_len": 10,
			"weights_file": "epoch-011.pkl"
		},
		"totals": {
			"eval": {
				"selected": 4951,
				"relevant": 4361,
				"true_positives": 1338,
				"false_positives": 3613,
				"false_negatives": 3023,
				"precision": 0.2702484346596647,
				"recall": 0.30681036459527633,
				"f1_score": 0.28737113402061853
			},
			"valid": {
				"selected": 4014,
				"relevant": 3804,
				"true_positives": 1105,
				"false_positives": 2909,
				"false_negatives": 2699,
				"precision": 0.2752864972595914,
				"recall": 0.29048370136698215,
				"f1_score": 0.28268099258122287
			}
		}
	},
	{
		"config": {
			"margin_of_error": [
				-0.5,
				0.5
			],
			"threshold": 0.65,
			"epoch": "11",
			"min_talk_len": null,
			"weights_file": "epoch-011.pkl"
		},
		"totals": {
			"eval": {
				"selected": 4321,
				"relevant": 5778,
				"true_positives": 731,
				"false_positives": 3590,
				"false_negatives": 5047,
				"precision": 0.16917380236056467,
				"recall": 0.12651436483212183,
				"f1_score": 0.14476680859491037
			},
			"valid": {
				"selected": 3648,
				"relevant": 5048,
				"true_positives": 637,
				"false_positives": 3011,
				"false_negatives": 4411,
				"precision": 0.17461622807017543,
				"recall": 0.12618858954041204,
				"f1_score": 0.1465041398344066
			}
		}
	},
	{
		"config": {
			"margin_of_error": [
				-0.5,
				0.5
			],
			"threshold": 0.65,
			"epoch": "11",
			"min_talk_len": 5,
			"weights_file": "epoch-011.pkl"
		},
		"totals": {
			"eval": {
				"selected": 2078,
				"relevant": 5192,
				"true_positives": 682,
				"false_positives": 1396,
				"false_negatives": 4510,
				"precision": 0.32820019249278154,
				"recall": 0.13135593220338984,
				"f1_score": 0.1876203576341128
			},
			"valid": {
				"selected": 1720,
				"relevant": 4567,
				"true_positives": 586,
				"false_positives": 1134,
				"false_negatives": 3981,
				"precision": 0.34069767441860466,
				"recall": 0.1283118020582439,
				"f1_score": 0.1864164148242405
			}
		}
	},
	{
		"config": {
			"margin_of_error": [
				-0.5,
				0.5
			],
			"threshold": 0.65,
			"epoch": "11",
			"min_talk_len": 10,
			"weights_file": "epoch-011.pkl"
		},
		"totals": {
			"eval": {
				"selected": 1771,
				"relevant": 4361,
				"true_positives": 573,
				"false_positives": 1198,
				"false_negatives": 3788,
				"precision": 0.3235460191981931,
				"recall": 0.13139188259573492,
				"f1_score": 0.18688845401174167
			},
			"valid": {
				"selected": 1434,
				"relevant": 3804,
				"true_positives": 496,
				"false_positives": 938,
				"false_negatives": 3308,
				"precision": 0.3458856345885635,
				"recall": 0.13038906414300735,
				"f1_score": 0.18938526155021002
			}
		}
	},
	{
		"config": {
			"margin_of_error": [
				-0.5,
				0.5
			],
			"threshold": 0.7,
			"epoch": "11",
			"min_talk_len": null,
			"weights_file": "epoch-011.pkl"
		},
		"totals": {
			"eval": {
				"selected": 920,
				"relevant": 5778,
				"true_positives": 176,
				"false_positives": 744,
				"false_negatives": 5602,
				"precision": 0.19130434782608696,
				"recall": 0.03046036690896504,
				"f1_score": 0.0525530008957898
			},
			"valid": {
				"selected": 789,
				"relevant": 5048,
				"true_positives": 160,
				"false_positives": 629,
				"false_negatives": 4888,
				"precision": 0.20278833967046894,
				"recall": 0.03169572107765452,
				"f1_score": 0.05482268288504369
			}
		}
	},
	{
		"config": {
			"margin_of_error": [
				-0.5,
				0.5
			],
			"threshold": 0.7,
			"epoch": "11",
			"min_talk_len": 5,
			"weights_file": "epoch-011.pkl"
		},
		"totals": {
			"eval": {
				"selected": 477,
				"relevant": 5192,
				"true_positives": 165,
				"false_positives": 312,
				"false_negatives": 5027,
				"precision": 0.34591194968553457,
				"recall": 0.03177966101694915,
				"f1_score": 0.058211324748632914
			},
			"valid": {
				"selected": 416,
				"relevant": 4567,
				"true_positives": 148,
				"false_positives": 268,
				"false_negatives": 4419,
				"precision": 0.3557692307692308,
				"recall": 0.03240639369389096,
				"f1_score": 0.0594019666867349
			}
		}
	},
	{
		"config": {
			"margin_of_error": [
				-0.5,
				0.5
			],
			"threshold": 0.7,
			"epoch": "11",
			"min_talk_len": 10,
			"weights_file": "epoch-011.pkl"
		},
		"totals": {
			"eval": {
				"selected": 415,
				"relevant": 4361,
				"true_positives": 139,
				"false_positives": 276,
				"false_negatives": 4222,
				"precision": 0.3349397590361446,
				"recall": 0.03187342352671406,
				"f1_score": 0.05820770519262981
			},
			"valid": {
				"selected": 359,
				"relevant": 3804,
				"true_positives": 129,
				"false_positives": 230,
				"false_negatives": 3675,
				"precision": 0.3593314763231198,
				"recall": 0.03391167192429022,
				"f1_score": 0.061974537593081906
			}
		}
	},
	{
		"config": {
			"margin_of_error": [
				0,
				1
			],
			"threshold": 0.5,
			"epoch": "11",
			"min_talk_len": null,
			"weights_file": "epoch-011.pkl"
		},
		"totals": {
			"eval": {
				"selected": 37668,
				"relevant": 5778,
				"true_positives": 1739,
				"false_positives": 35929,
				"false_negatives": 4039,
				"precision": 0.04616650738026973,
				"recall": 0.30096919349255796,
				"f1_score": 0.08005339962251991
			},
			"valid": {
				"selected": 30980,
				"relevant": 5048,
				"true_positives": 1464,
				"false_positives": 29516,
				"false_negatives": 3584,
				"precision": 0.04725629438347321,
				"recall": 0.2900158478605388,
				"f1_score": 0.08127012323748195
			}
		}
	},
	{
		"config": {
			"margin_of_error": [
				0,
				1
			],
			"threshold": 0.5,
			"epoch": "11",
			"min_talk_len": 5,
			"weights_file": "epoch-011.pkl"
		},
		"totals": {
			"eval": {
				"selected": 18256,
				"relevant": 5192,
				"true_positives": 1586,
				"false_positives": 16670,
				"false_negatives": 3606,
				"precision": 0.08687554776511831,
				"recall": 0.3054699537750385,
				"f1_score": 0.13527806209484816
			},
			"valid": {
				"selected": 15296,
				"relevant": 4567,
				"true_positives": 1352,
				"false_positives": 13944,
				"false_negatives": 3215,
				"precision": 0.08838912133891214,
				"recall": 0.29603678563608493,
				"f1_score": 0.1361325076775915
			}
		}
	},
	{
		"config": {
			"margin_of_error": [
				0,
				1
			],
			"threshold": 0.5,
			"epoch": "11",
			"min_talk_len": 10,
			"weights_file": "epoch-011.pkl"
		},
		"totals": {
			"eval": {
				"selected": 15537,
				"relevant": 4361,
				"true_positives": 1313,
				"false_positives": 14224,
				"false_negatives": 3048,
				"precision": 0.08450794876745832,
				"recall": 0.30107773446457237,
				"f1_score": 0.1319730626193587
			},
			"valid": {
				"selected": 12786,
				"relevant": 3804,
				"true_positives": 1110,
				"false_positives": 11676,
				"false_negatives": 2694,
				"precision": 0.08681370248709526,
				"recall": 0.2917981072555205,
				"f1_score": 0.13381555153707053
			}
		}
	},
	{
		"config": {
			"margin_of_error": [
				0,
				1
			],
			"threshold": 0.6,
			"epoch": "11",
			"min_talk_len": null,
			"weights_file": "epoch-011.pkl"
		},
		"totals": {
			"eval": {
				"selected": 12589,
				"relevant": 5778,
				"true_positives": 835,
				"false_positives": 11754,
				"false_negatives": 4943,
				"precision": 0.0663277464453094,
				"recall": 0.14451367255105574,
				"f1_score": 0.09092393967441606
			},
			"valid": {
				"selected": 10359,
				"relevant": 5048,
				"true_positives": 689,
				"false_positives": 9670,
				"false_negatives": 4359,
				"precision": 0.06651221160343662,
				"recall": 0.13648969889064977,
				"f1_score": 0.0894398649964302
			}
		}
	},
	{
		"config": {
			"margin_of_error": [
				0,
				1
			],
			"threshold": 0.6,
			"epoch": "11",
			"min_talk_len": 5,
			"weights_file": "epoch-011.pkl"
		},
		"totals": {
			"eval": {
				"selected": 5845,
				"relevant": 5192,
				"true_positives": 759,
				"false_positives": 5086,
				"false_negatives": 4433,
				"precision": 0.1298545765611634,
				"recall": 0.1461864406779661,
				"f1_score": 0.1375373742864909
			},
			"valid": {
				"selected": 4768,
				"relevant": 4567,
				"true_positives": 629,
				"false_positives": 4139,
				"false_negatives": 3938,
				"precision": 0.1319211409395973,
				"recall": 0.13772717319903657,
				"f1_score": 0.13476164970540974
			}
		}
	},
	{
		"config": {
			"margin_of_error": [
				0,
				1
			],
			"threshold": 0.6,
			"epoch": "11",
			"min_talk_len": 10,
			"weights_file": "epoch-011.pkl"
		},
		"totals": {
			"eval": {
				"selected": 4965,
				"relevant": 4361,
				"true_positives": 640,
				"false_positives": 4325,
				"false_negatives": 3721,
				"precision": 0.12890231621349446,
				"recall": 0.14675533134602156,
				"f1_score": 0.13725069697619557
			},
			"valid": {
				"selected": 4023,
				"relevant": 3804,
				"true_positives": 518,
				"false_positives": 3505,
				"false_negatives": 3286,
				"precision": 0.1287596321153368,
				"recall": 0.13617245005257625,
				"f1_score": 0.13236233550530213
			}
		}
	},
	{
		"config": {
			"margin_of_error": [
				0,
				1
			],
			"threshold": 0.65,
			"epoch": "11",
			"min_talk_len": null,
			"weights_file": "epoch-011.pkl"
		},
		"totals": {
			"eval": {
				"selected": 4321,
				"relevant": 5778,
				"true_positives": 374,
				"false_positives": 3947,
				"false_negatives": 5404,
				"precision": 0.08655403841703309,
				"recall": 0.0647282796815507,
				"f1_score": 0.07406673928111694
			},
			"valid": {
				"selected": 3648,
				"relevant": 5048,
				"true_positives": 293,
				"false_positives": 3355,
				"false_negatives": 4755,
				"precision": 0.08031798245614036,
				"recall": 0.058042789223454835,
				"f1_score": 0.06738730450781968
			}
		}
	},
	{
		"config": {
			"margin_of_error": [
				0,
				1
			],
			"threshold": 0.65,
			"epoch": "11",
			"min_talk_len": 5,
			"weights_file": "epoch-011.pkl"
		},
		"totals": {
			"eval": {
				"selected": 2085,
				"relevant": 5192,
				"true_positives": 342,
				"false_positives": 1743,
				"false_negatives": 4850,
				"precision": 0.16402877697841728,
				"recall": 0.06587057010785824,
				"f1_score": 0.09399477806788512
			},
			"valid": {
				"selected": 1724,
				"relevant": 4567,
				"true_positives": 269,
				"false_positives": 1455,
				"false_negatives": 4298,
				"precision": 0.15603248259860789,
				"recall": 0.058900810159842346,
				"f1_score": 0.08551899539024001
			}
		}
	},
	{
		"config": {
			"margin_of_error": [
				0,
				1
			],
			"threshold": 0.65,
			"epoch": "11",
			"min_talk_len": 10,
			"weights_file": "epoch-011.pkl"
		},
		"totals": {
			"eval": {
				"selected": 1776,
				"relevant": 4361,
				"true_positives": 280,
				"false_positives": 1496,
				"false_negatives": 4081,
				"precision": 0.15765765765765766,
				"recall": 0.06420545746388442,
				"f1_score": 0.09124979631741893
			},
			"valid": {
				"selected": 1437,
				"relevant": 3804,
				"true_positives": 224,
				"false_positives": 1213,
				"false_negatives": 3580,
				"precision": 0.1558803061934586,
				"recall": 0.058885383806519455,
				"f1_score": 0.08547987025376837
			}
		}
	},
	{
		"config": {
			"margin_of_error": [
				0,
				1
			],
			"threshold": 0.7,
			"epoch": "11",
			"min_talk_len": null,
			"weights_file": "epoch-011.pkl"
		},
		"totals": {
			"eval": {
				"selected": 920,
				"relevant": 5778,
				"true_positives": 96,
				"false_positives": 824,
				"false_negatives": 5682,
				"precision": 0.10434782608695652,
				"recall": 0.016614745586708203,
				"f1_score": 0.028665273215885335
			},
			"valid": {
				"selected": 789,
				"relevant": 5048,
				"true_positives": 77,
				"false_positives": 712,
				"false_negatives": 4971,
				"precision": 0.09759188846641319,
				"recall": 0.015253565768621236,
				"f1_score": 0.026383416138427273
			}
		}
	},
	{
		"config": {
			"margin_of_error": [
				0,
				1
			],
			"threshold": 0.7,
			"epoch": "11",
			"min_talk_len": 5,
			"weights_file": "epoch-011.pkl"
		},
		"totals": {
			"eval": {
				"selected": 479,
				"relevant": 5192,
				"true_positives": 90,
				"false_positives": 389,
				"false_negatives": 5102,
				"precision": 0.18789144050104384,
				"recall": 0.017334360554699536,
				"f1_score": 0.03174043378592841
			},
			"valid": {
				"selected": 417,
				"relevant": 4567,
				"true_positives": 70,
				"false_positives": 347,
				"false_negatives": 4497,
				"precision": 0.16786570743405277,
				"recall": 0.015327348368732209,
				"f1_score": 0.028089887640449437
			}
		}
	},
	{
		"config": {
			"margin_of_error": [
				0,
				1
			],
			"threshold": 0.7,
			"epoch": "11",
			"min_talk_len": 10,
			"weights_file": "epoch-011.pkl"
		},
		"totals": {
			"eval": {
				"selected": 417,
				"relevant": 4361,
				"true_positives": 75,
				"false_positives": 342,
				"false_negatives": 4286,
				"precision": 0.17985611510791366,
				"recall": 0.017197890392111902,
				"f1_score": 0.031393888656341566
			},
			"valid": {
				"selected": 360,
				"relevant": 3804,
				"true_positives": 58,
				"false_positives": 302,
				"false_negatives": 3746,
				"precision": 0.16111111111111112,
				"recall": 0.015247108307045216,
				"f1_score": 0.027857829010566763
			}
		}
	},
	{
		"config": {
			"margin_of_error": [
				-1,
				0
			],
			"threshold": 0.5,
			"epoch": "11",
			"min_talk_len": null,
			"weights_file": "epoch-011.pkl"
		},
		"totals": {
			"eval": {
				"selected": 37668,
				"relevant": 5778,
				"true_positives": 2552,
				"false_positives": 35116,
				"false_negatives": 3226,
				"precision": 0.06774981416587024,
				"recall": 0.44167532017999306,
				"f1_score": 0.1174791695438015
			},
			"valid": {
				"selected": 30980,
				"relevant": 5048,
				"true_positives": 2290,
				"false_positives": 28690,
				"false_negatives": 2758,
				"precision": 0.07391865719819238,
				"recall": 0.45364500792393025,
				"f1_score": 0.127123348506717
			}
		}
	},
	{
		"config": {
			"margin_of_error": [
				-1,
				0
			],
			"threshold": 0.5,
			"epoch": "11",
			"min_talk_len": 5,
			"weights_file": "epoch-011.pkl"
		},
		"totals": {
			"eval": {
				"selected": 18188,
				"relevant": 5192,
				"true_positives": 2333,
				"false_positives": 15855,
				"false_negatives": 2859,
				"precision": 0.12827138772817243,
				"recall": 0.44934514637904466,
				"f1_score": 0.19957228400342175
			},
			"valid": {
				"selected": 15239,
				"relevant": 4567,
				"true_positives": 2068,
				"false_positives": 13171,
				"false_negatives": 2499,
				"precision": 0.13570444254872366,
				"recall": 0.4528136632362601,
				"f1_score": 0.20882560840149447
			}
		}
	},
	{
		"config": {
			"margin_of_error": [
				-1,
				0
			],
			"threshold": 0.5,
			"epoch": "11",
			"min_talk_len": 10,
			"weights_file": "epoch-011.pkl"
		},
		"totals": {
			"eval": {
				"selected": 15497,
				"relevant": 4361,
				"true_positives": 1983,
				"false_positives": 13514,
				"false_negatives": 2378,
				"precision": 0.12796025037103956,
				"recall": 0.45471222196743866,
				"f1_score": 0.1997179977842683
			},
			"valid": {
				"selected": 12751,
				"relevant": 3804,
				"true_positives": 1749,
				"false_positives": 11002,
				"false_negatives": 2055,
				"precision": 0.1371657124931378,
				"recall": 0.4597791798107255,
				"f1_score": 0.21129568106312294
			}
		}
	},
	{
		"config": {
			"margin_of_error": [
				-1,
				0
			],
			"threshold": 0.6,
			"epoch": "11",
			"min_talk_len": null,
			"weights_file": "epoch-011.pkl"
		},
		"totals": {
			"eval": {
				"selected": 12589,
				"relevant": 5778,
				"true_positives": 1188,
				"false_positives": 11401,
				"false_negatives": 4590,
				"precision": 0.09436809913416475,
				"recall": 0.205607476635514,
				"f1_score": 0.12936244351282192
			},
			"valid": {
				"selected": 10359,
				"relevant": 5048,
				"true_positives": 1026,
				"false_positives": 9333,
				"false_negatives": 4022,
				"precision": 0.09904430929626412,
				"recall": 0.20324881141045958,
				"f1_score": 0.13318621405854483
			}
		}
	},
	{
		"config": {
			"margin_of_error": [
				-1,
				0
			],
			"threshold": 0.6,
			"epoch": "11",
			"min_talk_len": 5,
			"weights_file": "epoch-011.pkl"
		},
		"totals": {
			"eval": {
				"selected": 5805,
				"relevant": 5192,
				"true_positives": 1091,
				"false_positives": 4714,
				"false_negatives": 4101,
				"precision": 0.1879414298018949,
				"recall": 0.21013097072419107,
				"f1_score": 0.19841775029553513
			},
			"valid": {
				"selected": 4744,
				"relevant": 4567,
				"true_positives": 918,
				"false_positives": 3826,
				"false_negatives": 3649,
				"precision": 0.19350758853288363,
				"recall": 0.20100722574994526,
				"f1_score": 0.1971861239394265
			}
		}
	},
	{
		"config": {
			"margin_of_error": [
				-1,
				0
			],
			"threshold": 0.6,
			"epoch": "11",
			"min_talk_len": 10,
			"weights_file": "epoch-011.pkl"
		},
		"totals": {
			"eval": {
				"selected": 4934,
				"relevant": 4361,
				"true_positives": 927,
				"false_positives": 4007,
				"false_negatives": 3434,
				"precision": 0.18788001621402514,
				"recall": 0.21256592524650308,
				"f1_score": 0.1994620763851533
			},
			"valid": {
				"selected": 4007,
				"relevant": 3804,
				"true_positives": 789,
				"false_positives": 3218,
				"false_negatives": 3015,
				"precision": 0.19690541552283503,
				"recall": 0.20741324921135645,
				"f1_score": 0.20202278837536805
			}
		}
	},
	{
		"config": {
			"margin_of_error": [
				-1,
				0
			],
			"threshold": 0.65,
			"epoch": "11",
			"min_talk_len": null,
			"weights_file": "epoch-011.pkl"
		},
		"totals": {
			"eval": {
				"selected": 4321,
				"relevant": 5778,
				"true_positives": 477,
				"false_positives": 3844,
				"false_negatives": 5301,
				"precision": 0.1103911131682481,
				"recall": 0.08255451713395638,
				"f1_score": 0.0944647984949005
			},
			"valid": {
				"selected": 3648,
				"relevant": 5048,
				"true_positives": 457,
				"false_positives": 3191,
				"false_negatives": 4591,
				"precision": 0.12527412280701755,
				"recall": 0.09053090332805071,
				"f1_score": 0.10510579576816928
			}
		}
	},
	{
		"config": {
			"margin_of_error": [
				-1,
				0
			],
			"threshold": 0.65,
			"epoch": "11",
			"min_talk_len": 5,
			"weights_file": "epoch-011.pkl"
		},
		"totals": {
			"eval": {
				"selected": 2071,
				"relevant": 5192,
				"true_positives": 443,
				"false_positives": 1628,
				"false_negatives": 4749,
				"precision": 0.21390632544664415,
				"recall": 0.08532357473035439,
				"f1_score": 0.12198815916288036
			},
			"valid": {
				"selected": 1712,
				"relevant": 4567,
				"true_positives": 403,
				"false_positives": 1309,
				"false_negatives": 4164,
				"precision": 0.23539719626168223,
				"recall": 0.08824173417998686,
				"f1_score": 0.12836438923395446
			}
		}
	},
	{
		"config": {
			"margin_of_error": [
				-1,
				0
			],
			"threshold": 0.65,
			"epoch": "11",
			"min_talk_len": 10,
			"weights_file": "epoch-011.pkl"
		},
		"totals": {
			"eval": {
				"selected": 1765,
				"relevant": 4361,
				"true_positives": 380,
				"false_positives": 1385,
				"false_negatives": 3981,
				"precision": 0.21529745042492918,
				"recall": 0.0871359779867003,
				"f1_score": 0.12406137773424747
			},
			"valid": {
				"selected": 1429,
				"relevant": 3804,
				"true_positives": 341,
				"false_positives": 1088,
				"false_negatives": 3463,
				"precision": 0.23862841147655703,
				"recall": 0.08964248159831756,
				"f1_score": 0.13032677240588572
			}
		}
	},
	{
		"config": {
			"margin_of_error": [
				-1,
				0
			],
			"threshold": 0.7,
			"epoch": "11",
			"min_talk_len": null,
			"weights_file": "epoch-011.pkl"
		},
		"totals": {
			"eval": {
				"selected": 920,
				"relevant": 5778,
				"true_positives": 114,
				"false_positives": 806,
				"false_negatives": 5664,
				"precision": 0.12391304347826088,
				"recall": 0.01973001038421599,
				"f1_score": 0.03404001194386384
			},
			"valid": {
				"selected": 789,
				"relevant": 5048,
				"true_positives": 111,
				"false_positives": 678,
				"false_negatives": 4937,
				"precision": 0.14068441064638784,
				"recall": 0.02198890649762282,
				"f1_score": 0.038033236251499056
			}
		}
	},
	{
		"config": {
			"margin_of_error": [
				-1,
				0
			],
			"threshold": 0.7,
			"epoch": "11",
			"min_talk_len": 5,
			"weights_file": "epoch-011.pkl"
		},
		"totals": {
			"eval": {
				"selected": 475,
				"relevant": 5192,
				"true_positives": 105,
				"false_positives": 370,
				"false_negatives": 5087,
				"precision": 0.22105263157894736,
				"recall": 0.02022342064714946,
				"f1_score": 0.037056643726839596
			},
			"valid": {
				"selected": 411,
				"relevant": 4567,
				"true_positives": 98,
				"false_positives": 313,
				"false_negatives": 4469,
				"precision": 0.2384428223844282,
				"recall": 0.021458287716225093,
				"f1_score": 0.03937324226597026
			}
		}
	},
	{
		"config": {
			"margin_of_error": [
				-1,
				0
			],
			"threshold": 0.7,
			"epoch": "11",
			"min_talk_len": 10,
			"weights_file": "epoch-011.pkl"
		},
		"totals": {
			"eval": {
				"selected": 414,
				"relevant": 4361,
				"true_positives": 88,
				"false_positives": 326,
				"false_negatives": 4273,
				"precision": 0.21256038647342995,
				"recall": 0.020178858060077964,
				"f1_score": 0.036858638743455505
			},
			"valid": {
				"selected": 355,
				"relevant": 3804,
				"true_positives": 89,
				"false_positives": 266,
				"false_negatives": 3715,
				"precision": 0.2507042253521127,
				"recall": 0.023396424815983176,
				"f1_score": 0.04279874969944698
			}
		}
	},
	{
		"config": {
			"margin_of_error": [
				-0.2,
				0.2
			],
			"threshold": 0.5,
			"epoch": "11",
			"min_talk_len": null,
			"weights_file": "epoch-011.pkl"
		},
		"totals": {
			"eval": {
				"selected": 37668,
				"relevant": 5778,
				"true_positives": 2077,
				"false_positives": 35591,
				"false_negatives": 3701,
				"precision": 0.055139641074652225,
				"recall": 0.3594669435790931,
				"f1_score": 0.09561294480504533
			},
			"valid": {
				"selected": 30980,
				"relevant": 5048,
				"true_positives": 1814,
				"false_positives": 29166,
				"false_negatives": 3234,
				"precision": 0.05855390574564235,
				"recall": 0.3593502377179081,
				"f1_score": 0.10069945597868324
			}
		}
	},
	{
		"config": {
			"margin_of_error": [
				-0.2,
				0.2
			],
			"threshold": 0.5,
			"epoch": "11",
			"min_talk_len": 5,
			"weights_file": "epoch-011.pkl"
		},
		"totals": {
			"eval": {
				"selected": 18237,
				"relevant": 5192,
				"true_positives": 1939,
				"false_positives": 16298,
				"false_negatives": 3253,
				"precision": 0.10632231178373636,
				"recall": 0.3734591679506934,
				"f1_score": 0.16552136241410217
			},
			"valid": {
				"selected": 15279,
				"relevant": 4567,
				"true_positives": 1696,
				"false_positives": 13583,
				"false_negatives": 2871,
				"precision": 0.1110020289285948,
				"recall": 0.3713597547624261,
				"f1_score": 0.1709160536128187
			}
		}
	},
	{
		"config": {
			"margin_of_error": [
				-0.2,
				0.2
			],
			"threshold": 0.5,
			"epoch": "11",
			"min_talk_len": 10,
			"weights_file": "epoch-011.pkl"
		},
		"totals": {
			"eval": {
				"selected": 15528,
				"relevant": 4361,
				"true_positives": 1650,
				"false_positives": 13878,
				"false_negatives": 2711,
				"precision": 0.1062596599690881,
				"recall": 0.37835358862646185,
				"f1_score": 0.16592086077731408
			},
			"valid": {
				"selected": 12771,
				"relevant": 3804,
				"true_positives": 1435,
				"false_positives": 11336,
				"false_negatives": 2369,
				"precision": 0.1123639495732519,
				"recall": 0.37723449001051523,
				"f1_score": 0.1731523378582202
			}
		}
	},
	{
		"config": {
			"margin_of_error": [
				-0.2,
				0.2
			],
			"threshold": 0.6,
			"epoch": "11",
			"min_talk_len": null,
			"weights_file": "epoch-011.pkl"
		},
		"totals": {
			"eval": {
				"selected": 12589,
				"relevant": 5778,
				"true_positives": 1012,
				"false_positives": 11577,
				"false_negatives": 4766,
				"precision": 0.08038764000317737,
				"recall": 0.17514710972654898,
				"f1_score": 0.11019763706647792
			},
			"valid": {
				"selected": 10359,
				"relevant": 5048,
				"true_positives": 869,
				"false_positives": 9490,
				"false_negatives": 4179,
				"precision": 0.0838884062168163,
				"recall": 0.17214738510301109,
				"f1_score": 0.11280586746284156
			}
		}
	},
	{
		"config": {
			"margin_of_error": [
				-0.2,
				0.2
			],
			"threshold": 0.6,
			"epoch": "11",
			"min_talk_len": 5,
			"weights_file": "epoch-011.pkl"
		},
		"totals": {
			"eval": {
				"selected": 5836,
				"relevant": 5192,
				"true_positives": 955,
				"false_positives": 4881,
				"false_negatives": 4237,
				"precision": 0.16363947909527074,
				"recall": 0.18393682588597843,
				"f1_score": 0.17319550235763512
			},
			"valid": {
				"selected": 4765,
				"relevant": 4567,
				"true_positives": 809,
				"false_positives": 3956,
				"false_negatives": 3758,
				"precision": 0.16977964323189926,
				"recall": 0.17714035471863368,
				"f1_score": 0.17338191170167166
			}
		}
	},
	{
		"config": {
			"margin_of_error": [
				-0.2,
				0.2
			],
			"threshold": 0.6,
			"epoch": "11",
			"min_talk_len": 10,
			"weights_file": "epoch-011.pkl"
		},
		"totals": {
			"eval": {
				"selected": 4959,
				"relevant": 4361,
				"true_positives": 823,
				"false_positives": 4136,
				"false_negatives": 3538,
				"precision": 0.16596087920951805,
				"recall": 0.1887181839027746,
				"f1_score": 0.17660944206008583
			},
			"valid": {
				"selected": 4021,
				"relevant": 3804,
				"true_positives": 690,
				"false_positives": 3331,
				"false_negatives": 3114,
				"precision": 0.1715991047003233,
				"recall": 0.18138801261829654,
				"f1_score": 0.17635782747603834
			}
		}
	},
	{
		"config": {
			"margin_of_error": [
				-0.2,
				0.2
			],
			"threshold": 0.65,
			"epoch": "11",
			"min_talk_len": null,
			"weights_file": "epoch-011.pkl"
		},
		"totals": {
			"eval": {
				"selected": 4321,
				"relevant": 5778,
				"true_positives": 433,
				"false_positives": 3888,
				"false_negatives": 5345,
				"precision": 0.10020828511918538,
				"recall": 0.07493942540671512,
				"f1_score": 0.08575106446182791
			},
			"valid": {
				"selected": 3648,
				"relevant": 5048,
				"true_positives": 387,
				"false_positives": 3261,
				"false_negatives": 4661,
				"precision": 0.10608552631578948,
				"recall": 0.07666402535657686,
				"f1_score": 0.0890064397424103
			}
		}
	},
	{
		"config": {
			"margin_of_error": [
				-0.2,
				0.2
			],
			"threshold": 0.65,
			"epoch": "11",
			"min_talk_len": 5,
			"weights_file": "epoch-011.pkl"
		},
		"totals": {
			"eval": {
				"selected": 2081,
				"relevant": 5192,
				"true_positives": 411,
				"false_positives": 1670,
				"false_negatives": 4781,
				"precision": 0.19750120134550697,
				"recall": 0.07916024653312789,
				"f1_score": 0.11302076172143542
			},
			"valid": {
				"selected": 1723,
				"relevant": 4567,
				"true_positives": 357,
				"false_positives": 1366,
				"false_negatives": 4210,
				"precision": 0.20719674985490424,
				"recall": 0.07816947668053427,
				"f1_score": 0.1135135135135135
			}
		}
	},
	{
		"config": {
			"margin_of_error": [
				-0.2,
				0.2
			],
			"threshold": 0.65,
			"epoch": "11",
			"min_talk_len": 10,
			"weights_file": "epoch-011.pkl"
		},
		"totals": {
			"eval": {
				"selected": 1775,
				"relevant": 4361,
				"true_positives": 356,
				"false_positives": 1419,
				"false_negatives": 4005,
				"precision": 0.20056338028169013,
				"recall": 0.08163265306122448,
				"f1_score": 0.11603650586701433
			},
			"valid": {
				"selected": 1436,
				"relevant": 3804,
				"true_positives": 307,
				"false_positives": 1129,
				"false_negatives": 3497,
				"precision": 0.2137883008356546,
				"recall": 0.08070452155625657,
				"f1_score": 0.11717557251908398
			}
		}
	},
	{
		"config": {
			"margin_of_error": [
				-0.2,
				0.2
			],
			"threshold": 0.7,
			"epoch": "11",
			"min_talk_len": null,
			"weights_file": "epoch-011.pkl"
		},
		"totals": {
			"eval": {
				"selected": 920,
				"relevant": 5778,
				"true_positives": 109,
				"false_positives": 811,
				"false_negatives": 5669,
				"precision": 0.11847826086956521,
				"recall": 0.01886465905157494,
				"f1_score": 0.032547028963869816
			},
			"valid": {
				"selected": 789,
				"relevant": 5048,
				"true_positives": 106,
				"false_positives": 683,
				"false_negatives": 4942,
				"precision": 0.13434727503168567,
				"recall": 0.020998415213946117,
				"f1_score": 0.036320027411341445
			}
		}
	},
	{
		"config": {
			"margin_of_error": [
				-0.2,
				0.2
			],
			"threshold": 0.7,
			"epoch": "11",
			"min_talk_len": 5,
			"weights_file": "epoch-011.pkl"
		},
		"totals": {
			"eval": {
				"selected": 477,
				"relevant": 5192,
				"true_positives": 105,
				"false_positives": 372,
				"false_negatives": 5087,
				"precision": 0.22012578616352202,
				"recall": 0.02022342064714946,
				"f1_score": 0.037043570294584584
			},
			"valid": {
				"selected": 417,
				"relevant": 4567,
				"true_positives": 98,
				"false_positives": 319,
				"false_negatives": 4469,
				"precision": 0.23501199040767387,
				"recall": 0.021458287716225093,
				"f1_score": 0.03932584269662921
			}
		}
	},
	{
		"config": {
			"margin_of_error": [
				-0.2,
				0.2
			],
			"threshold": 0.7,
			"epoch": "11",
			"min_talk_len": 10,
			"weights_file": "epoch-011.pkl"
		},
		"totals": {
			"eval": {
				"selected": 416,
				"relevant": 4361,
				"true_positives": 90,
				"false_positives": 326,
				"false_negatives": 4271,
				"precision": 0.21634615384615385,
				"recall": 0.02063746847053428,
				"f1_score": 0.037680552648105506
			},
			"valid": {
				"selected": 360,
				"relevant": 3804,
				"true_positives": 87,
				"false_positives": 273,
				"false_negatives": 3717,
				"precision": 0.24166666666666667,
				"recall": 0.022870662460567823,
				"f1_score": 0.04178674351585014
			}
		}
	}
]