[
	{
		"config": {
			"margin_of_error": [
				-0.1,
				0.5
			],
			"threshold": 0.5,
			"epoch": "2",
			"min_talk_len": null,
			"weights_file": "epoch-002.pkl"
		},
		"totals": {
			"eval": {
				"selected": 50183,
				"relevant": 5780,
				"true_positives": 2557,
				"false_positives": 47626,
				"false_negatives": 3223,
				"precision": 0.0509535101528406,
				"recall": 0.44238754325259516,
				"f1_score": 0.09138180583599878
			},
			"valid": {
				"selected": 42096,
				"relevant": 5048,
				"true_positives": 2243,
				"false_positives": 39853,
				"false_negatives": 2805,
				"precision": 0.053282972253895854,
				"recall": 0.4443343898573692,
				"f1_score": 0.09515526896317665
			}
		}
	},
	{
		"config": {
			"margin_of_error": [
				-0.1,
				0.5
			],
			"threshold": 0.5,
			"epoch": "2",
			"min_talk_len": 5,
			"weights_file": "epoch-002.pkl"
		},
		"totals": {
			"eval": {
				"selected": 20098,
				"relevant": 5196,
				"true_positives": 2364,
				"false_positives": 17734,
				"false_negatives": 2832,
				"precision": 0.11762364414369589,
				"recall": 0.45496535796766746,
				"f1_score": 0.1869217996362774
			},
			"valid": {
				"selected": 16946,
				"relevant": 4567,
				"true_positives": 2086,
				"false_positives": 14860,
				"false_negatives": 2481,
				"precision": 0.12309689602266022,
				"recall": 0.45675498138821985,
				"f1_score": 0.1939292520801376
			}
		}
	},
	{
		"config": {
			"margin_of_error": [
				-0.1,
				0.5
			],
			"threshold": 0.5,
			"epoch": "2",
			"min_talk_len": 10,
			"weights_file": "epoch-002.pkl"
		},
		"totals": {
			"eval": {
				"selected": 17206,
				"relevant": 4365,
				"true_positives": 1983,
				"false_positives": 15223,
				"false_negatives": 2382,
				"precision": 0.11525049401371615,
				"recall": 0.4542955326460481,
				"f1_score": 0.1838579574428631
			},
			"valid": {
				"selected": 14217,
				"relevant": 3804,
				"true_positives": 1738,
				"false_positives": 12479,
				"false_negatives": 2066,
				"precision": 0.12224801294225224,
				"recall": 0.4568874868559411,
				"f1_score": 0.19288607735419788
			}
		}
	},
	{
		"config": {
			"margin_of_error": [
				-0.1,
				0.5
			],
			"threshold": 0.6,
			"epoch": "2",
			"min_talk_len": null,
			"weights_file": "epoch-002.pkl"
		},
		"totals": {
			"eval": {
				"selected": 23140,
				"relevant": 5780,
				"true_positives": 1904,
				"false_positives": 21236,
				"false_negatives": 3876,
				"precision": 0.08228176318063958,
				"recall": 0.32941176470588235,
				"f1_score": 0.13167358229598894
			},
			"valid": {
				"selected": 19252,
				"relevant": 5048,
				"true_positives": 1673,
				"false_positives": 17579,
				"false_negatives": 3375,
				"precision": 0.08690006233118637,
				"recall": 0.33141838351822506,
				"f1_score": 0.13769547325102882
			}
		}
	},
	{
		"config": {
			"margin_of_error": [
				-0.1,
				0.5
			],
			"threshold": 0.6,
			"epoch": "2",
			"min_talk_len": 5,
			"weights_file": "epoch-002.pkl"
		},
		"totals": {
			"eval": {
				"selected": 11153,
				"relevant": 5196,
				"true_positives": 1766,
				"false_positives": 9387,
				"false_negatives": 3430,
				"precision": 0.15834304671388863,
				"recall": 0.33987682832948424,
				"f1_score": 0.21603767814545233
			},
			"valid": {
				"selected": 9239,
				"relevant": 4567,
				"true_positives": 1559,
				"false_positives": 7680,
				"false_negatives": 3008,
				"precision": 0.16874120575819893,
				"recall": 0.3413619443836216,
				"f1_score": 0.22584383601332753
			}
		}
	},
	{
		"config": {
			"margin_of_error": [
				-0.1,
				0.5
			],
			"threshold": 0.6,
			"epoch": "2",
			"min_talk_len": 10,
			"weights_file": "epoch-002.pkl"
		},
		"totals": {
			"eval": {
				"selected": 9499,
				"relevant": 4365,
				"true_positives": 1482,
				"false_positives": 8017,
				"false_negatives": 2883,
				"precision": 0.1560164227813454,
				"recall": 0.3395189003436426,
				"f1_score": 0.21379111367570683
			},
			"valid": {
				"selected": 7765,
				"relevant": 3804,
				"true_positives": 1304,
				"false_positives": 6461,
				"false_negatives": 2500,
				"precision": 0.16793303283966515,
				"recall": 0.34279705573080965,
				"f1_score": 0.2254300285245051
			}
		}
	},
	{
		"config": {
			"margin_of_error": [
				-0.1,
				0.5
			],
			"threshold": 0.65,
			"epoch": "2",
			"min_talk_len": null,
			"weights_file": "epoch-002.pkl"
		},
		"totals": {
			"eval": {
				"selected": 14321,
				"relevant": 5780,
				"true_positives": 1400,
				"false_positives": 12921,
				"false_negatives": 4380,
				"precision": 0.09775853641505482,
				"recall": 0.2422145328719723,
				"f1_score": 0.13929655241032785
			},
			"valid": {
				"selected": 11892,
				"relevant": 5048,
				"true_positives": 1243,
				"false_positives": 10649,
				"false_negatives": 3805,
				"precision": 0.10452404978136562,
				"recall": 0.24623613312202852,
				"f1_score": 0.14675324675324675
			}
		}
	},
	{
		"config": {
			"margin_of_error": [
				-0.1,
				0.5
			],
			"threshold": 0.65,
			"epoch": "2",
			"min_talk_len": 5,
			"weights_file": "epoch-002.pkl"
		},
		"totals": {
			"eval": {
				"selected": 7084,
				"relevant": 5196,
				"true_positives": 1304,
				"false_positives": 5780,
				"false_negatives": 3892,
				"precision": 0.18407679277244496,
				"recall": 0.25096227867590454,
				"f1_score": 0.21237785016286645
			},
			"valid": {
				"selected": 5794,
				"relevant": 4567,
				"true_positives": 1159,
				"false_positives": 4635,
				"false_negatives": 3408,
				"precision": 0.20003451846738005,
				"recall": 0.25377709656229475,
				"f1_score": 0.22372357880513463
			}
		}
	},
	{
		"config": {
			"margin_of_error": [
				-0.1,
				0.5
			],
			"threshold": 0.65,
			"epoch": "2",
			"min_talk_len": 10,
			"weights_file": "epoch-002.pkl"
		},
		"totals": {
			"eval": {
				"selected": 6043,
				"relevant": 4365,
				"true_positives": 1097,
				"false_positives": 4946,
				"false_negatives": 3268,
				"precision": 0.18153235148105246,
				"recall": 0.2513172966781214,
				"f1_score": 0.21079938508839355
			},
			"valid": {
				"selected": 4885,
				"relevant": 3804,
				"true_positives": 974,
				"false_positives": 3911,
				"false_negatives": 2830,
				"precision": 0.19938587512794267,
				"recall": 0.25604626708727657,
				"f1_score": 0.2241915065024744
			}
		}
	},
	{
		"config": {
			"margin_of_error": [
				-0.1,
				0.5
			],
			"threshold": 0.7,
			"epoch": "2",
			"min_talk_len": null,
			"weights_file": "epoch-002.pkl"
		},
		"totals": {
			"eval": {
				"selected": 7793,
				"relevant": 5780,
				"true_positives": 889,
				"false_positives": 6904,
				"false_negatives": 4891,
				"precision": 0.11407673553188759,
				"recall": 0.15380622837370242,
				"f1_score": 0.13099535843218152
			},
			"valid": {
				"selected": 6476,
				"relevant": 5048,
				"true_positives": 765,
				"false_positives": 5711,
				"false_negatives": 4283,
				"precision": 0.11812847436689314,
				"recall": 0.15154516640253565,
				"f1_score": 0.1327664005553627
			}
		}
	},
	{
		"config": {
			"margin_of_error": [
				-0.1,
				0.5
			],
			"threshold": 0.7,
			"epoch": "2",
			"min_talk_len": 5,
			"weights_file": "epoch-002.pkl"
		},
		"totals": {
			"eval": {
				"selected": 3911,
				"relevant": 5196,
				"true_positives": 832,
				"false_positives": 3079,
				"false_negatives": 4364,
				"precision": 0.21273331628739453,
				"recall": 0.1601231716705158,
				"f1_score": 0.18271659163280995
			},
			"valid": {
				"selected": 3172,
				"relevant": 4567,
				"true_positives": 708,
				"false_positives": 2464,
				"false_negatives": 3859,
				"precision": 0.223203026481715,
				"recall": 0.15502518064374862,
				"f1_score": 0.18296937588835768
			}
		}
	},
	{
		"config": {
			"margin_of_error": [
				-0.1,
				0.5
			],
			"threshold": 0.7,
			"epoch": "2",
			"min_talk_len": 10,
			"weights_file": "epoch-002.pkl"
		},
		"totals": {
			"eval": {
				"selected": 3329,
				"relevant": 4365,
				"true_positives": 701,
				"false_positives": 2628,
				"false_negatives": 3664,
				"precision": 0.2105737458696305,
				"recall": 0.16059564719358535,
				"f1_score": 0.18221991161944373
			},
			"valid": {
				"selected": 2668,
				"relevant": 3804,
				"true_positives": 596,
				"false_positives": 2072,
				"false_negatives": 3208,
				"precision": 0.22338830584707647,
				"recall": 0.15667718191377497,
				"f1_score": 0.1841779975278121
			}
		}
	},
	{
		"config": {
			"margin_of_error": [
				-0.5,
				0.5
			],
			"threshold": 0.5,
			"epoch": "2",
			"min_talk_len": null,
			"weights_file": "epoch-002.pkl"
		},
		"totals": {
			"eval": {
				"selected": 50183,
				"relevant": 5780,
				"true_positives": 3914,
				"false_positives": 46269,
				"false_negatives": 1866,
				"precision": 0.07799453998365981,
				"recall": 0.6771626297577855,
				"f1_score": 0.13987813376695316
			},
			"valid": {
				"selected": 42096,
				"relevant": 5048,
				"true_positives": 3443,
				"false_positives": 38653,
				"false_negatives": 1605,
				"precision": 0.08178924363359939,
				"recall": 0.6820522979397782,
				"f1_score": 0.14606312574240624
			}
		}
	},
	{
		"config": {
			"margin_of_error": [
				-0.5,
				0.5
			],
			"threshold": 0.5,
			"epoch": "2",
			"min_talk_len": 5,
			"weights_file": "epoch-002.pkl"
		},
		"totals": {
			"eval": {
				"selected": 20072,
				"relevant": 5196,
				"true_positives": 3581,
				"false_positives": 16491,
				"false_negatives": 1615,
				"precision": 0.17840773216420885,
				"recall": 0.689183987682833,
				"f1_score": 0.2834415070444832
			},
			"valid": {
				"selected": 16930,
				"relevant": 4567,
				"true_positives": 3165,
				"false_positives": 13765,
				"false_negatives": 1402,
				"precision": 0.18694624926166567,
				"recall": 0.6930151083862491,
				"f1_score": 0.29445969205005346
			}
		}
	},
	{
		"config": {
			"margin_of_error": [
				-0.5,
				0.5
			],
			"threshold": 0.5,
			"epoch": "2",
			"min_talk_len": 10,
			"weights_file": "epoch-002.pkl"
		},
		"totals": {
			"eval": {
				"selected": 17192,
				"relevant": 4365,
				"true_positives": 3029,
				"false_positives": 14163,
				"false_negatives": 1336,
				"precision": 0.17618659841786877,
				"recall": 0.6939289805269186,
				"f1_score": 0.2810224057150809
			},
			"valid": {
				"selected": 14206,
				"relevant": 3804,
				"true_positives": 2651,
				"false_positives": 11555,
				"false_negatives": 1153,
				"precision": 0.18661129100380122,
				"recall": 0.6968980021030494,
				"f1_score": 0.29439200444197666
			}
		}
	},
	{
		"config": {
			"margin_of_error": [
				-0.5,
				0.5
			],
			"threshold": 0.6,
			"epoch": "2",
			"min_talk_len": null,
			"weights_file": "epoch-002.pkl"
		},
		"totals": {
			"eval": {
				"selected": 23140,
				"relevant": 5780,
				"true_positives": 2888,
				"false_positives": 20252,
				"false_negatives": 2892,
				"precision": 0.12480553154710458,
				"recall": 0.4996539792387543,
				"f1_score": 0.19972337482710925
			},
			"valid": {
				"selected": 19252,
				"relevant": 5048,
				"true_positives": 2536,
				"false_positives": 16716,
				"false_negatives": 2512,
				"precision": 0.13172657386245584,
				"recall": 0.5023771790808241,
				"f1_score": 0.20872427983539094
			}
		}
	},
	{
		"config": {
			"margin_of_error": [
				-0.5,
				0.5
			],
			"threshold": 0.6,
			"epoch": "2",
			"min_talk_len": 5,
			"weights_file": "epoch-002.pkl"
		},
		"totals": {
			"eval": {
				"selected": 11131,
				"relevant": 5196,
				"true_positives": 2654,
				"false_positives": 8477,
				"false_negatives": 2542,
				"precision": 0.23843320456383074,
				"recall": 0.5107775211701309,
				"f1_score": 0.32510565321247015
			},
			"valid": {
				"selected": 9222,
				"relevant": 4567,
				"true_positives": 2322,
				"false_positives": 6900,
				"false_negatives": 2245,
				"precision": 0.2517891997397528,
				"recall": 0.5084300416028027,
				"f1_score": 0.33679019508303726
			}
		}
	},
	{
		"config": {
			"margin_of_error": [
				-0.5,
				0.5
			],
			"threshold": 0.6,
			"epoch": "2",
			"min_talk_len": 10,
			"weights_file": "epoch-002.pkl"
		},
		"totals": {
			"eval": {
				"selected": 9487,
				"relevant": 4365,
				"true_positives": 2247,
				"false_positives": 7240,
				"false_negatives": 2118,
				"precision": 0.23685042689996838,
				"recall": 0.5147766323024054,
				"f1_score": 0.32442968524400806
			},
			"valid": {
				"selected": 7753,
				"relevant": 3804,
				"true_positives": 1953,
				"false_positives": 5800,
				"false_negatives": 1851,
				"precision": 0.2519024893589578,
				"recall": 0.5134069400630915,
				"f1_score": 0.337976983646275
			}
		}
	},
	{
		"config": {
			"margin_of_error": [
				-0.5,
				0.5
			],
			"threshold": 0.65,
			"epoch": "2",
			"min_talk_len": null,
			"weights_file": "epoch-002.pkl"
		},
		"totals": {
			"eval": {
				"selected": 14321,
				"relevant": 5780,
				"true_positives": 2143,
				"false_positives": 12178,
				"false_negatives": 3637,
				"precision": 0.14964038824104461,
				"recall": 0.3707612456747405,
				"f1_score": 0.21322322272523755
			},
			"valid": {
				"selected": 11892,
				"relevant": 5048,
				"true_positives": 1881,
				"false_positives": 10011,
				"false_negatives": 3167,
				"precision": 0.15817356205852673,
				"recall": 0.3726228209191759,
				"f1_score": 0.22207792207792204
			}
		}
	},
	{
		"config": {
			"margin_of_error": [
				-0.5,
				0.5
			],
			"threshold": 0.65,
			"epoch": "2",
			"min_talk_len": 5,
			"weights_file": "epoch-002.pkl"
		},
		"totals": {
			"eval": {
				"selected": 7066,
				"relevant": 5196,
				"true_positives": 1972,
				"false_positives": 5094,
				"false_negatives": 3224,
				"precision": 0.2790829323521087,
				"recall": 0.37952270977675134,
				"f1_score": 0.32164410373511665
			},
			"valid": {
				"selected": 5779,
				"relevant": 4567,
				"true_positives": 1715,
				"false_positives": 4064,
				"false_negatives": 2852,
				"precision": 0.29676414604602874,
				"recall": 0.3755200350339391,
				"f1_score": 0.33152909336941816
			}
		}
	},
	{
		"config": {
			"margin_of_error": [
				-0.5,
				0.5
			],
			"threshold": 0.65,
			"epoch": "2",
			"min_talk_len": 10,
			"weights_file": "epoch-002.pkl"
		},
		"totals": {
			"eval": {
				"selected": 6032,
				"relevant": 4365,
				"true_positives": 1680,
				"false_positives": 4352,
				"false_negatives": 2685,
				"precision": 0.27851458885941643,
				"recall": 0.3848797250859107,
				"f1_score": 0.3231701452342022
			},
			"valid": {
				"selected": 4875,
				"relevant": 3804,
				"true_positives": 1449,
				"false_positives": 3426,
				"false_negatives": 2355,
				"precision": 0.29723076923076924,
				"recall": 0.38091482649842273,
				"f1_score": 0.33390943657103356
			}
		}
	},
	{
		"config": {
			"margin_of_error": [
				-0.5,
				0.5
			],
			"threshold": 0.7,
			"epoch": "2",
			"min_talk_len": null,
			"weights_file": "epoch-002.pkl"
		},
		"totals": {
			"eval": {
				"selected": 7793,
				"relevant": 5780,
				"true_positives": 1341,
				"false_positives": 6452,
				"false_negatives": 4439,
				"precision": 0.17207750545361222,
				"recall": 0.23200692041522492,
				"f1_score": 0.1975981728431445
			},
			"valid": {
				"selected": 6476,
				"relevant": 5048,
				"true_positives": 1167,
				"false_positives": 5309,
				"false_negatives": 3881,
				"precision": 0.18020382952439779,
				"recall": 0.23118066561014264,
				"f1_score": 0.20253384241582784
			}
		}
	},
	{
		"config": {
			"margin_of_error": [
				-0.5,
				0.5
			],
			"threshold": 0.7,
			"epoch": "2",
			"min_talk_len": 5,
			"weights_file": "epoch-002.pkl"
		},
		"totals": {
			"eval": {
				"selected": 3897,
				"relevant": 5196,
				"true_positives": 1235,
				"false_positives": 2662,
				"false_negatives": 3961,
				"precision": 0.31691044393122914,
				"recall": 0.23768283294842185,
				"f1_score": 0.271637523369625
			},
			"valid": {
				"selected": 3158,
				"relevant": 4567,
				"true_positives": 1049,
				"false_positives": 2109,
				"false_negatives": 3518,
				"precision": 0.33217226092463586,
				"recall": 0.2296912634114298,
				"f1_score": 0.27158576051779937
			}
		}
	},
	{
		"config": {
			"margin_of_error": [
				-0.5,
				0.5
			],
			"threshold": 0.7,
			"epoch": "2",
			"min_talk_len": 10,
			"weights_file": "epoch-002.pkl"
		},
		"totals": {
			"eval": {
				"selected": 3321,
				"relevant": 4365,
				"true_positives": 1049,
				"false_positives": 2272,
				"false_negatives": 3316,
				"precision": 0.31586871424269797,
				"recall": 0.24032073310423827,
				"f1_score": 0.27296383034087957
			},
			"valid": {
				"selected": 2658,
				"relevant": 3804,
				"true_positives": 887,
				"false_positives": 1771,
				"false_negatives": 2917,
				"precision": 0.33370955605718583,
				"recall": 0.23317560462670872,
				"f1_score": 0.2745280099040545
			}
		}
	},
	{
		"config": {
			"margin_of_error": [
				0,
				1
			],
			"threshold": 0.5,
			"epoch": "2",
			"min_talk_len": null,
			"weights_file": "epoch-002.pkl"
		},
		"totals": {
			"eval": {
				"selected": 50183,
				"relevant": 5780,
				"true_positives": 2234,
				"false_positives": 47949,
				"false_negatives": 3546,
				"precision": 0.04451706753282984,
				"recall": 0.38650519031141867,
				"f1_score": 0.07983846469989099
			},
			"valid": {
				"selected": 42096,
				"relevant": 5048,
				"true_positives": 1955,
				"false_positives": 40141,
				"false_negatives": 3093,
				"precision": 0.04644146712276701,
				"recall": 0.3872820919175911,
				"f1_score": 0.08293738333616156
			}
		}
	},
	{
		"config": {
			"margin_of_error": [
				0,
				1
			],
			"threshold": 0.5,
			"epoch": "2",
			"min_talk_len": 5,
			"weights_file": "epoch-002.pkl"
		},
		"totals": {
			"eval": {
				"selected": 20116,
				"relevant": 5196,
				"true_positives": 2046,
				"false_positives": 18070,
				"false_negatives": 3150,
				"precision": 0.10171008152714257,
				"recall": 0.39376443418013857,
				"f1_score": 0.16166245259165615
			},
			"valid": {
				"selected": 16969,
				"relevant": 4567,
				"true_positives": 1795,
				"false_positives": 15174,
				"false_negatives": 2772,
				"precision": 0.10578113029642289,
				"recall": 0.3930370045982045,
				"f1_score": 0.16669762258543833
			}
		}
	},
	{
		"config": {
			"margin_of_error": [
				0,
				1
			],
			"threshold": 0.5,
			"epoch": "2",
			"min_talk_len": 10,
			"weights_file": "epoch-002.pkl"
		},
		"totals": {
			"eval": {
				"selected": 17219,
				"relevant": 4365,
				"true_positives": 1685,
				"false_positives": 15534,
				"false_negatives": 2680,
				"precision": 0.09785701840989605,
				"recall": 0.38602520045819017,
				"f1_score": 0.15613417346182357
			},
			"valid": {
				"selected": 14233,
				"relevant": 3804,
				"true_positives": 1475,
				"false_positives": 12758,
				"false_negatives": 2329,
				"precision": 0.10363240356917024,
				"recall": 0.38774973711882227,
				"f1_score": 0.16355269723346455
			}
		}
	},
	{
		"config": {
			"margin_of_error": [
				0,
				1
			],
			"threshold": 0.6,
			"epoch": "2",
			"min_talk_len": null,
			"weights_file": "epoch-002.pkl"
		},
		"totals": {
			"eval": {
				"selected": 23140,
				"relevant": 5780,
				"true_positives": 1656,
				"false_positives": 21484,
				"false_negatives": 4124,
				"precision": 0.07156439066551426,
				"recall": 0.2865051903114187,
				"f1_score": 0.11452282157676347
			},
			"valid": {
				"selected": 19252,
				"relevant": 5048,
				"true_positives": 1432,
				"false_positives": 17820,
				"false_negatives": 3616,
				"precision": 0.07438188240182839,
				"recall": 0.2836767036450079,
				"f1_score": 0.11786008230452676
			}
		}
	},
	{
		"config": {
			"margin_of_error": [
				0,
				1
			],
			"threshold": 0.6,
			"epoch": "2",
			"min_talk_len": 5,
			"weights_file": "epoch-002.pkl"
		},
		"totals": {
			"eval": {
				"selected": 11168,
				"relevant": 5196,
				"true_positives": 1516,
				"false_positives": 9652,
				"false_negatives": 3680,
				"precision": 0.13574498567335244,
				"recall": 0.29176289453425713,
				"f1_score": 0.18528477144952338
			},
			"valid": {
				"selected": 9258,
				"relevant": 4567,
				"true_positives": 1317,
				"false_positives": 7941,
				"false_negatives": 3250,
				"precision": 0.1422553467271549,
				"recall": 0.28837311145171884,
				"f1_score": 0.1905244122965642
			}
		}
	},
	{
		"config": {
			"margin_of_error": [
				0,
				1
			],
			"threshold": 0.6,
			"epoch": "2",
			"min_talk_len": 10,
			"weights_file": "epoch-002.pkl"
		},
		"totals": {
			"eval": {
				"selected": 9510,
				"relevant": 4365,
				"true_positives": 1243,
				"false_positives": 8267,
				"false_negatives": 3122,
				"precision": 0.13070452155625656,
				"recall": 0.2847651775486827,
				"f1_score": 0.17917117117117115
			},
			"valid": {
				"selected": 7777,
				"relevant": 3804,
				"true_positives": 1079,
				"false_positives": 6698,
				"false_negatives": 2725,
				"precision": 0.13874244567313873,
				"recall": 0.28364879074658256,
				"f1_score": 0.18633969432691475
			}
		}
	},
	{
		"config": {
			"margin_of_error": [
				0,
				1
			],
			"threshold": 0.65,
			"epoch": "2",
			"min_talk_len": null,
			"weights_file": "epoch-002.pkl"
		},
		"totals": {
			"eval": {
				"selected": 14321,
				"relevant": 5780,
				"true_positives": 1209,
				"false_positives": 13112,
				"false_negatives": 4571,
				"precision": 0.0844214789470009,
				"recall": 0.2091695501730104,
				"f1_score": 0.1202925227600617
			},
			"valid": {
				"selected": 11892,
				"relevant": 5048,
				"true_positives": 1082,
				"false_positives": 10810,
				"false_negatives": 3966,
				"precision": 0.09098553649512277,
				"recall": 0.21434231378763866,
				"f1_score": 0.12774498229043685
			}
		}
	},
	{
		"config": {
			"margin_of_error": [
				0,
				1
			],
			"threshold": 0.65,
			"epoch": "2",
			"min_talk_len": 5,
			"weights_file": "epoch-002.pkl"
		},
		"totals": {
			"eval": {
				"selected": 7092,
				"relevant": 5196,
				"true_positives": 1112,
				"false_positives": 5980,
				"false_negatives": 4084,
				"precision": 0.15679639029892836,
				"recall": 0.21401077752117012,
				"f1_score": 0.18098958333333331
			},
			"valid": {
				"selected": 5809,
				"relevant": 4567,
				"true_positives": 994,
				"false_positives": 4815,
				"false_negatives": 3573,
				"precision": 0.17111378894818385,
				"recall": 0.21764834683599737,
				"f1_score": 0.19159599074787972
			}
		}
	},
	{
		"config": {
			"margin_of_error": [
				0,
				1
			],
			"threshold": 0.65,
			"epoch": "2",
			"min_talk_len": 10,
			"weights_file": "epoch-002.pkl"
		},
		"totals": {
			"eval": {
				"selected": 6048,
				"relevant": 4365,
				"true_positives": 912,
				"false_positives": 5136,
				"false_negatives": 3453,
				"precision": 0.15079365079365079,
				"recall": 0.20893470790378008,
				"f1_score": 0.1751656583117257
			},
			"valid": {
				"selected": 4894,
				"relevant": 3804,
				"true_positives": 817,
				"false_positives": 4077,
				"false_negatives": 2987,
				"precision": 0.16693910911319984,
				"recall": 0.2147739221871714,
				"f1_score": 0.18785927799494134
			}
		}
	},
	{
		"config": {
			"margin_of_error": [
				0,
				1
			],
			"threshold": 0.7,
			"epoch": "2",
			"min_talk_len": null,
			"weights_file": "epoch-002.pkl"
		},
		"totals": {
			"eval": {
				"selected": 7793,
				"relevant": 5780,
				"true_positives": 778,
				"false_positives": 7015,
				"false_negatives": 5002,
				"precision": 0.09983318362633133,
				"recall": 0.13460207612456748,
				"f1_score": 0.11463935754807339
			},
			"valid": {
				"selected": 6476,
				"relevant": 5048,
				"true_positives": 669,
				"false_positives": 5807,
				"false_negatives": 4379,
				"precision": 0.10330450895614576,
				"recall": 0.13252773375594296,
				"f1_score": 0.1161055189170427
			}
		}
	},
	{
		"config": {
			"margin_of_error": [
				0,
				1
			],
			"threshold": 0.7,
			"epoch": "2",
			"min_talk_len": 5,
			"weights_file": "epoch-002.pkl"
		},
		"totals": {
			"eval": {
				"selected": 3917,
				"relevant": 5196,
				"true_positives": 714,
				"false_positives": 3203,
				"false_negatives": 4482,
				"precision": 0.18228235894817463,
				"recall": 0.1374133949191686,
				"f1_score": 0.15669922089322946
			},
			"valid": {
				"selected": 3183,
				"relevant": 4567,
				"true_positives": 607,
				"false_positives": 2576,
				"false_negatives": 3960,
				"precision": 0.19070059692114358,
				"recall": 0.1329100065688636,
				"f1_score": 0.1566451612903226
			}
		}
	},
	{
		"config": {
			"margin_of_error": [
				0,
				1
			],
			"threshold": 0.7,
			"epoch": "2",
			"min_talk_len": 10,
			"weights_file": "epoch-002.pkl"
		},
		"totals": {
			"eval": {
				"selected": 3333,
				"relevant": 4365,
				"true_positives": 591,
				"false_positives": 2742,
				"false_negatives": 3774,
				"precision": 0.1773177317731773,
				"recall": 0.13539518900343642,
				"f1_score": 0.1535463756819953
			},
			"valid": {
				"selected": 2674,
				"relevant": 3804,
				"true_positives": 497,
				"false_positives": 2177,
				"false_negatives": 3307,
				"precision": 0.18586387434554974,
				"recall": 0.13065194532071503,
				"f1_score": 0.1534424205001544
			}
		}
	},
	{
		"config": {
			"margin_of_error": [
				-1,
				0
			],
			"threshold": 0.5,
			"epoch": "2",
			"min_talk_len": null,
			"weights_file": "epoch-002.pkl"
		},
		"totals": {
			"eval": {
				"selected": 50183,
				"relevant": 5780,
				"true_positives": 2412,
				"false_positives": 47771,
				"false_negatives": 3368,
				"precision": 0.04806408544726302,
				"recall": 0.41730103806228375,
				"f1_score": 0.08619981058913925
			},
			"valid": {
				"selected": 42096,
				"relevant": 5048,
				"true_positives": 2166,
				"false_positives": 39930,
				"false_negatives": 2882,
				"precision": 0.05145381984036488,
				"recall": 0.42908082408874804,
				"f1_score": 0.09188868148650942
			}
		}
	},
	{
		"config": {
			"margin_of_error": [
				-1,
				0
			],
			"threshold": 0.5,
			"epoch": "2",
			"min_talk_len": 5,
			"weights_file": "epoch-002.pkl"
		},
		"totals": {
			"eval": {
				"selected": 20039,
				"relevant": 5196,
				"true_positives": 2157,
				"false_positives": 17882,
				"false_negatives": 3039,
				"precision": 0.1076401018014871,
				"recall": 0.4151270207852194,
				"f1_score": 0.17095304141073905
			},
			"valid": {
				"selected": 16899,
				"relevant": 4567,
				"true_positives": 1939,
				"false_positives": 14960,
				"false_negatives": 2628,
				"precision": 0.11474051719036629,
				"recall": 0.4245675498138822,
				"f1_score": 0.18065778440324234
			}
		}
	},
	{
		"config": {
			"margin_of_error": [
				-1,
				0
			],
			"threshold": 0.5,
			"epoch": "2",
			"min_talk_len": 10,
			"weights_file": "epoch-002.pkl"
		},
		"totals": {
			"eval": {
				"selected": 17170,
				"relevant": 4365,
				"true_positives": 1862,
				"false_positives": 15308,
				"false_negatives": 2503,
				"precision": 0.10844496214327315,
				"recall": 0.4265750286368843,
				"f1_score": 0.17292779196656607
			},
			"valid": {
				"selected": 14189,
				"relevant": 3804,
				"true_positives": 1650,
				"false_positives": 12539,
				"false_negatives": 2154,
				"precision": 0.11628726478257806,
				"recall": 0.43375394321766564,
				"f1_score": 0.18340465736675374
			}
		}
	},
	{
		"config": {
			"margin_of_error": [
				-1,
				0
			],
			"threshold": 0.6,
			"epoch": "2",
			"min_talk_len": null,
			"weights_file": "epoch-002.pkl"
		},
		"totals": {
			"eval": {
				"selected": 23140,
				"relevant": 5780,
				"true_positives": 1705,
				"false_positives": 21435,
				"false_negatives": 4075,
				"precision": 0.07368193604148661,
				"recall": 0.29498269896193774,
				"f1_score": 0.11791147994467499
			},
			"valid": {
				"selected": 19252,
				"relevant": 5048,
				"true_positives": 1559,
				"false_positives": 17693,
				"false_negatives": 3489,
				"precision": 0.08097859962601288,
				"recall": 0.3088351822503962,
				"f1_score": 0.1283127572016461
			}
		}
	},
	{
		"config": {
			"margin_of_error": [
				-1,
				0
			],
			"threshold": 0.6,
			"epoch": "2",
			"min_talk_len": 5,
			"weights_file": "epoch-002.pkl"
		},
		"totals": {
			"eval": {
				"selected": 11098,
				"relevant": 5196,
				"true_positives": 1533,
				"false_positives": 9565,
				"false_negatives": 3663,
				"precision": 0.13813299693638492,
				"recall": 0.29503464203233254,
				"f1_score": 0.18816742359150607
			},
			"valid": {
				"selected": 9194,
				"relevant": 4567,
				"true_positives": 1377,
				"false_positives": 7817,
				"false_negatives": 3190,
				"precision": 0.14977159016750055,
				"recall": 0.3015108386249179,
				"f1_score": 0.20013080444735123
			}
		}
	},
	{
		"config": {
			"margin_of_error": [
				-1,
				0
			],
			"threshold": 0.6,
			"epoch": "2",
			"min_talk_len": 10,
			"weights_file": "epoch-002.pkl"
		},
		"totals": {
			"eval": {
				"selected": 9463,
				"relevant": 4365,
				"true_positives": 1324,
				"false_positives": 8139,
				"false_negatives": 3041,
				"precision": 0.13991334671879954,
				"recall": 0.3033218785796105,
				"f1_score": 0.19149551634365056
			},
			"valid": {
				"selected": 7737,
				"relevant": 3804,
				"true_positives": 1177,
				"false_positives": 6560,
				"false_negatives": 2627,
				"precision": 0.15212614708543362,
				"recall": 0.3094111461619348,
				"f1_score": 0.20396846027207347
			}
		}
	},
	{
		"config": {
			"margin_of_error": [
				-1,
				0
			],
			"threshold": 0.65,
			"epoch": "2",
			"min_talk_len": null,
			"weights_file": "epoch-002.pkl"
		},
		"totals": {
			"eval": {
				"selected": 14321,
				"relevant": 5780,
				"true_positives": 1273,
				"false_positives": 13048,
				"false_negatives": 4507,
				"precision": 0.08889044061168913,
				"recall": 0.22024221453287196,
				"f1_score": 0.12666036515596238
			},
			"valid": {
				"selected": 11892,
				"relevant": 5048,
				"true_positives": 1122,
				"false_positives": 10770,
				"false_negatives": 3926,
				"precision": 0.09434914228052473,
				"recall": 0.2222662440570523,
				"f1_score": 0.13246753246753248
			}
		}
	},
	{
		"config": {
			"margin_of_error": [
				-1,
				0
			],
			"threshold": 0.65,
			"epoch": "2",
			"min_talk_len": 5,
			"weights_file": "epoch-002.pkl"
		},
		"totals": {
			"eval": {
				"selected": 7037,
				"relevant": 5196,
				"true_positives": 1136,
				"false_positives": 5901,
				"false_negatives": 4060,
				"precision": 0.16143242859172943,
				"recall": 0.21862971516551194,
				"f1_score": 0.18572713152946949
			},
			"valid": {
				"selected": 5752,
				"relevant": 4567,
				"true_positives": 980,
				"false_positives": 4772,
				"false_negatives": 3587,
				"precision": 0.17037552155771907,
				"recall": 0.21458287716225094,
				"f1_score": 0.18994088574474272
			}
		}
	},
	{
		"config": {
			"margin_of_error": [
				-1,
				0
			],
			"threshold": 0.65,
			"epoch": "2",
			"min_talk_len": 10,
			"weights_file": "epoch-002.pkl"
		},
		"totals": {
			"eval": {
				"selected": 6011,
				"relevant": 4365,
				"true_positives": 991,
				"false_positives": 5020,
				"false_negatives": 3374,
				"precision": 0.164864415238729,
				"recall": 0.2270332187857961,
				"f1_score": 0.191017733230532
			},
			"valid": {
				"selected": 4859,
				"relevant": 3804,
				"true_positives": 848,
				"false_positives": 4011,
				"false_negatives": 2956,
				"precision": 0.1745215064828154,
				"recall": 0.22292323869610936,
				"f1_score": 0.19577513563430682
			}
		}
	},
	{
		"config": {
			"margin_of_error": [
				-1,
				0
			],
			"threshold": 0.7,
			"epoch": "2",
			"min_talk_len": null,
			"weights_file": "epoch-002.pkl"
		},
		"totals": {
			"eval": {
				"selected": 7793,
				"relevant": 5780,
				"true_positives": 762,
				"false_positives": 7031,
				"false_negatives": 5018,
				"precision": 0.09778005902733222,
				"recall": 0.13183391003460207,
				"f1_score": 0.11228173579901275
			},
			"valid": {
				"selected": 6476,
				"relevant": 5048,
				"true_positives": 709,
				"false_positives": 5767,
				"false_negatives": 4339,
				"precision": 0.10948116121062385,
				"recall": 0.14045166402535658,
				"f1_score": 0.12304755293300938
			}
		}
	},
	{
		"config": {
			"margin_of_error": [
				-1,
				0
			],
			"threshold": 0.7,
			"epoch": "2",
			"min_talk_len": 5,
			"weights_file": "epoch-002.pkl"
		},
		"totals": {
			"eval": {
				"selected": 3879,
				"relevant": 5196,
				"true_positives": 677,
				"false_positives": 3202,
				"false_negatives": 4519,
				"precision": 0.17452951791698892,
				"recall": 0.13029253271747498,
				"f1_score": 0.14920110192837469
			},
			"valid": {
				"selected": 3134,
				"relevant": 4567,
				"true_positives": 606,
				"false_positives": 2528,
				"false_negatives": 3961,
				"precision": 0.19336311423101468,
				"recall": 0.13269104444931026,
				"f1_score": 0.15738215816127774
			}
		}
	},
	{
		"config": {
			"margin_of_error": [
				-1,
				0
			],
			"threshold": 0.7,
			"epoch": "2",
			"min_talk_len": 10,
			"weights_file": "epoch-002.pkl"
		},
		"totals": {
			"eval": {
				"selected": 3309,
				"relevant": 4365,
				"true_positives": 586,
				"false_positives": 2723,
				"false_negatives": 3779,
				"precision": 0.17709277727410094,
				"recall": 0.13424971363115693,
				"f1_score": 0.15272348188689078
			},
			"valid": {
				"selected": 2644,
				"relevant": 3804,
				"true_positives": 523,
				"false_positives": 2121,
				"false_negatives": 3281,
				"precision": 0.19780635400907715,
				"recall": 0.13748685594111462,
				"f1_score": 0.1622208436724566
			}
		}
	},
	{
		"config": {
			"margin_of_error": [
				-0.2,
				0.2
			],
			"threshold": 0.5,
			"epoch": "2",
			"min_talk_len": null,
			"weights_file": "epoch-002.pkl"
		},
		"totals": {
			"eval": {
				"selected": 50183,
				"relevant": 5780,
				"true_positives": 2363,
				"false_positives": 47820,
				"false_negatives": 3417,
				"precision": 0.04708765916744714,
				"recall": 0.4088235294117647,
				"f1_score": 0.08444865357468327
			},
			"valid": {
				"selected": 42096,
				"relevant": 5048,
				"true_positives": 2086,
				"false_positives": 40010,
				"false_negatives": 2962,
				"precision": 0.04955340174838464,
				"recall": 0.4132329635499208,
				"f1_score": 0.0884948243678941
			}
		}
	},
	{
		"config": {
			"margin_of_error": [
				-0.2,
				0.2
			],
			"threshold": 0.5,
			"epoch": "2",
			"min_talk_len": 5,
			"weights_file": "epoch-002.pkl"
		},
		"totals": {
			"eval": {
				"selected": 20080,
				"relevant": 5196,
				"true_positives": 2181,
				"false_positives": 17899,
				"false_negatives": 3015,
				"precision": 0.10861553784860557,
				"recall": 0.4197459584295612,
				"f1_score": 0.17257477448963446
			},
			"valid": {
				"selected": 16936,
				"relevant": 4567,
				"true_positives": 1947,
				"false_positives": 14989,
				"false_negatives": 2620,
				"precision": 0.11496221067548418,
				"recall": 0.42631924677030875,
				"f1_score": 0.18109101055666652
			}
		}
	},
	{
		"config": {
			"margin_of_error": [
				-0.2,
				0.2
			],
			"threshold": 0.5,
			"epoch": "2",
			"min_talk_len": 10,
			"weights_file": "epoch-002.pkl"
		},
		"totals": {
			"eval": {
				"selected": 17193,
				"relevant": 4365,
				"true_positives": 1857,
				"false_positives": 15336,
				"false_negatives": 2508,
				"precision": 0.10800907346012913,
				"recall": 0.4254295532646048,
				"f1_score": 0.1722794322293348
			},
			"valid": {
				"selected": 14211,
				"relevant": 3804,
				"true_positives": 1658,
				"false_positives": 12553,
				"false_negatives": 2146,
				"precision": 0.11667018506790515,
				"recall": 0.43585699263932703,
				"f1_score": 0.18406883152928116
			}
		}
	},
	{
		"config": {
			"margin_of_error": [
				-0.2,
				0.2
			],
			"threshold": 0.6,
			"epoch": "2",
			"min_talk_len": null,
			"weights_file": "epoch-002.pkl"
		},
		"totals": {
			"eval": {
				"selected": 23140,
				"relevant": 5780,
				"true_positives": 1766,
				"false_positives": 21374,
				"false_negatives": 4014,
				"precision": 0.0763180639585134,
				"recall": 0.3055363321799308,
				"f1_score": 0.12213001383125865
			},
			"valid": {
				"selected": 19252,
				"relevant": 5048,
				"true_positives": 1534,
				"false_positives": 17718,
				"false_negatives": 3514,
				"precision": 0.07968003324329939,
				"recall": 0.3038827258320127,
				"f1_score": 0.1262551440329218
			}
		}
	},
	{
		"config": {
			"margin_of_error": [
				-0.2,
				0.2
			],
			"threshold": 0.6,
			"epoch": "2",
			"min_talk_len": 5,
			"weights_file": "epoch-002.pkl"
		},
		"totals": {
			"eval": {
				"selected": 11137,
				"relevant": 5196,
				"true_positives": 1639,
				"false_positives": 9498,
				"false_negatives": 3557,
				"precision": 0.14716710065547275,
				"recall": 0.31543494996150884,
				"f1_score": 0.20069797342802917
			},
			"valid": {
				"selected": 9231,
				"relevant": 4567,
				"true_positives": 1432,
				"false_positives": 7799,
				"false_negatives": 3135,
				"precision": 0.15512945509695591,
				"recall": 0.31355375520035034,
				"f1_score": 0.20756631395854472
			}
		}
	},
	{
		"config": {
			"margin_of_error": [
				-0.2,
				0.2
			],
			"threshold": 0.6,
			"epoch": "2",
			"min_talk_len": 10,
			"weights_file": "epoch-002.pkl"
		},
		"totals": {
			"eval": {
				"selected": 9488,
				"relevant": 4365,
				"true_positives": 1401,
				"false_positives": 8087,
				"false_negatives": 2964,
				"precision": 0.1476602023608769,
				"recall": 0.3209621993127148,
				"f1_score": 0.20226665704179603
			},
			"valid": {
				"selected": 7759,
				"relevant": 3804,
				"true_positives": 1220,
				"false_positives": 6539,
				"false_negatives": 2584,
				"precision": 0.15723675731408687,
				"recall": 0.3207150368033649,
				"f1_score": 0.21101790192856526
			}
		}
	},
	{
		"config": {
			"margin_of_error": [
				-0.2,
				0.2
			],
			"threshold": 0.65,
			"epoch": "2",
			"min_talk_len": null,
			"weights_file": "epoch-002.pkl"
		},
		"totals": {
			"eval": {
				"selected": 14321,
				"relevant": 5780,
				"true_positives": 1303,
				"false_positives": 13018,
				"false_negatives": 4477,
				"precision": 0.09098526639201174,
				"recall": 0.2254325259515571,
				"f1_score": 0.12964529127904087
			},
			"valid": {
				"selected": 11892,
				"relevant": 5048,
				"true_positives": 1127,
				"false_positives": 10765,
				"false_negatives": 3921,
				"precision": 0.09476959300369997,
				"recall": 0.223256735340729,
				"f1_score": 0.1330578512396694
			}
		}
	},
	{
		"config": {
			"margin_of_error": [
				-0.2,
				0.2
			],
			"threshold": 0.65,
			"epoch": "2",
			"min_talk_len": 5,
			"weights_file": "epoch-002.pkl"
		},
		"totals": {
			"eval": {
				"selected": 7070,
				"relevant": 5196,
				"true_positives": 1206,
				"false_positives": 5864,
				"false_negatives": 3990,
				"precision": 0.17057991513437057,
				"recall": 0.23210161662817552,
				"f1_score": 0.19664112180009785
			},
			"valid": {
				"selected": 5787,
				"relevant": 4567,
				"true_positives": 1048,
				"false_positives": 4739,
				"false_negatives": 3519,
				"precision": 0.18109555901157767,
				"recall": 0.2294723012918765,
				"f1_score": 0.2024338419934325
			}
		}
	},
	{
		"config": {
			"margin_of_error": [
				-0.2,
				0.2
			],
			"threshold": 0.65,
			"epoch": "2",
			"min_talk_len": 10,
			"weights_file": "epoch-002.pkl"
		},
		"totals": {
			"eval": {
				"selected": 6032,
				"relevant": 4365,
				"true_positives": 1040,
				"false_positives": 4992,
				"false_negatives": 3325,
				"precision": 0.1724137931034483,
				"recall": 0.23825887743413515,
				"f1_score": 0.2000577089545061
			},
			"valid": {
				"selected": 4880,
				"relevant": 3804,
				"true_positives": 902,
				"false_positives": 3978,
				"false_negatives": 2902,
				"precision": 0.1848360655737705,
				"recall": 0.23711882229232387,
				"f1_score": 0.2077383694150161
			}
		}
	},
	{
		"config": {
			"margin_of_error": [
				-0.2,
				0.2
			],
			"threshold": 0.7,
			"epoch": "2",
			"min_talk_len": null,
			"weights_file": "epoch-002.pkl"
		},
		"totals": {
			"eval": {
				"selected": 7793,
				"relevant": 5780,
				"true_positives": 787,
				"false_positives": 7006,
				"false_negatives": 4993,
				"precision": 0.10098806621326832,
				"recall": 0.13615916955017301,
				"f1_score": 0.11596551978191999
			},
			"valid": {
				"selected": 6476,
				"relevant": 5048,
				"true_positives": 687,
				"false_positives": 5789,
				"false_negatives": 4361,
				"precision": 0.1060840024706609,
				"recall": 0.13609350237717907,
				"f1_score": 0.1192294342242277
			}
		}
	},
	{
		"config": {
			"margin_of_error": [
				-0.2,
				0.2
			],
			"threshold": 0.7,
			"epoch": "2",
			"min_talk_len": 5,
			"weights_file": "epoch-002.pkl"
		},
		"totals": {
			"eval": {
				"selected": 3901,
				"relevant": 5196,
				"true_positives": 732,
				"false_positives": 3169,
				"false_negatives": 4464,
				"precision": 0.18764419379646244,
				"recall": 0.14087759815242495,
				"f1_score": 0.16093217544245356
			},
			"valid": {
				"selected": 3166,
				"relevant": 4567,
				"true_positives": 635,
				"false_positives": 2531,
				"false_negatives": 3932,
				"precision": 0.20056854074542008,
				"recall": 0.13904094591635646,
				"f1_score": 0.1642312168627958
			}
		}
	},
	{
		"config": {
			"margin_of_error": [
				-0.2,
				0.2
			],
			"threshold": 0.7,
			"epoch": "2",
			"min_talk_len": 10,
			"weights_file": "epoch-002.pkl"
		},
		"totals": {
			"eval": {
				"selected": 3321,
				"relevant": 4365,
				"true_positives": 631,
				"false_positives": 2690,
				"false_negatives": 3734,
				"precision": 0.19000301114122253,
				"recall": 0.1445589919816724,
				"f1_score": 0.16419463960447567
			},
			"valid": {
				"selected": 2664,
				"relevant": 3804,
				"true_positives": 550,
				"false_positives": 2114,
				"false_negatives": 3254,
				"precision": 0.20645645645645647,
				"recall": 0.14458464773922186,
				"f1_score": 0.17006802721088435
			}
		}
	}
]