[
	{
		"config": {
			"margin_of_error": [
				-0.1,
				0.5
			],
			"threshold": 0.5,
			"epoch": "best",
			"min_talk_len": null,
			"weights_file": "epoch-027.pkl"
		},
		"totals": {
			"selected": 16646,
			"relevant": 5744,
			"true_positives": 346,
			"false_positives": 16300,
			"false_negatives": 5398,
			"precision": 0.020785774360206656,
			"recall": 0.06023676880222841,
			"f1_score": 0.03090665475658776
		}
	},
	{
		"config": {
			"margin_of_error": [
				-0.1,
				0.5
			],
			"threshold": 0.5,
			"epoch": "best",
			"min_talk_len": 5,
			"weights_file": "epoch-027.pkl"
		},
		"totals": {
			"selected": 6854,
			"relevant": 5179,
			"true_positives": 286,
			"false_positives": 6568,
			"false_negatives": 4893,
			"precision": 0.04172745841844178,
			"recall": 0.0552230160262599,
			"f1_score": 0.047535942823900945
		}
	},
	{
		"config": {
			"margin_of_error": [
				-0.1,
				0.5
			],
			"threshold": 0.5,
			"epoch": "best",
			"min_talk_len": 10,
			"weights_file": "epoch-027.pkl"
		},
		"totals": {
			"selected": 6053,
			"relevant": 4767,
			"true_positives": 265,
			"false_positives": 5788,
			"false_negatives": 4502,
			"precision": 0.04377994382950603,
			"recall": 0.055590518145584224,
			"f1_score": 0.04898336414048059
		}
	},
	{
		"config": {
			"margin_of_error": [
				-0.1,
				0.5
			],
			"threshold": 0.6,
			"epoch": "best",
			"min_talk_len": null,
			"weights_file": "epoch-027.pkl"
		},
		"totals": {
			"selected": 350,
			"relevant": 5744,
			"true_positives": 3,
			"false_positives": 347,
			"false_negatives": 5741,
			"precision": 0.008571428571428572,
			"recall": 0.0005222841225626741,
			"f1_score": 0.0009845749917952082
		}
	},
	{
		"config": {
			"margin_of_error": [
				-0.1,
				0.5
			],
			"threshold": 0.6,
			"epoch": "best",
			"min_talk_len": 5,
			"weights_file": "epoch-027.pkl"
		},
		"totals": {
			"selected": 75,
			"relevant": 5179,
			"true_positives": 0,
			"false_positives": 75,
			"false_negatives": 5179,
			"precision": 0,
			"recall": 1,
			"f1_score": 0.0
		}
	},
	{
		"config": {
			"margin_of_error": [
				-0.1,
				0.5
			],
			"threshold": 0.6,
			"epoch": "best",
			"min_talk_len": 10,
			"weights_file": "epoch-027.pkl"
		},
		"totals": {
			"selected": 56,
			"relevant": 4767,
			"true_positives": 0,
			"false_positives": 56,
			"false_negatives": 4767,
			"precision": 0,
			"recall": 1,
			"f1_score": 0.0
		}
	},
	{
		"config": {
			"margin_of_error": [
				-0.1,
				0.5
			],
			"threshold": 0.7,
			"epoch": "best",
			"min_talk_len": null,
			"weights_file": "epoch-027.pkl"
		},
		"totals": {
			"selected": 9,
			"relevant": 5744,
			"true_positives": 0,
			"false_positives": 9,
			"false_negatives": 5744,
			"precision": 0,
			"recall": 1,
			"f1_score": 0.0
		}
	},
	{
		"config": {
			"margin_of_error": [
				-0.1,
				0.5
			],
			"threshold": 0.7,
			"epoch": "best",
			"min_talk_len": 5,
			"weights_file": "epoch-027.pkl"
		},
		"totals": {
			"selected": 1,
			"relevant": 5179,
			"true_positives": 0,
			"false_positives": 1,
			"false_negatives": 5179,
			"precision": 0,
			"recall": 1,
			"f1_score": 0.0
		}
	},
	{
		"config": {
			"margin_of_error": [
				-0.1,
				0.5
			],
			"threshold": 0.7,
			"epoch": "best",
			"min_talk_len": 10,
			"weights_file": "epoch-027.pkl"
		},
		"totals": {
			"selected": 1,
			"relevant": 4767,
			"true_positives": 0,
			"false_positives": 1,
			"false_negatives": 4767,
			"precision": 0,
			"recall": 1,
			"f1_score": 0.0
		}
	},
	{
		"config": {
			"margin_of_error": [
				-0.5,
				0.5
			],
			"threshold": 0.5,
			"epoch": "best",
			"min_talk_len": null,
			"weights_file": "epoch-027.pkl"
		},
		"totals": {
			"selected": 16646,
			"relevant": 5744,
			"true_positives": 411,
			"false_positives": 16235,
			"false_negatives": 5333,
			"precision": 0.02469061636429172,
			"recall": 0.07155292479108635,
			"f1_score": 0.03671281822242072
		}
	},
	{
		"config": {
			"margin_of_error": [
				-0.5,
				0.5
			],
			"threshold": 0.5,
			"epoch": "best",
			"min_talk_len": 5,
			"weights_file": "epoch-027.pkl"
		},
		"totals": {
			"selected": 6854,
			"relevant": 5179,
			"true_positives": 341,
			"false_positives": 6513,
			"false_negatives": 4838,
			"precision": 0.049751969652757515,
			"recall": 0.06584282680054064,
			"f1_score": 0.05667747029003574
		}
	},
	{
		"config": {
			"margin_of_error": [
				-0.5,
				0.5
			],
			"threshold": 0.5,
			"epoch": "best",
			"min_talk_len": 10,
			"weights_file": "epoch-027.pkl"
		},
		"totals": {
			"selected": 6053,
			"relevant": 4767,
			"true_positives": 314,
			"false_positives": 5739,
			"false_negatives": 4453,
			"precision": 0.051875103254584505,
			"recall": 0.06586951961401301,
			"f1_score": 0.05804066543438077
		}
	},
	{
		"config": {
			"margin_of_error": [
				-0.5,
				0.5
			],
			"threshold": 0.6,
			"epoch": "best",
			"min_talk_len": null,
			"weights_file": "epoch-027.pkl"
		},
		"totals": {
			"selected": 350,
			"relevant": 5744,
			"true_positives": 5,
			"false_positives": 345,
			"false_negatives": 5739,
			"precision": 0.014285714285714285,
			"recall": 0.0008704735376044568,
			"f1_score": 0.0016409583196586807
		}
	},
	{
		"config": {
			"margin_of_error": [
				-0.5,
				0.5
			],
			"threshold": 0.6,
			"epoch": "best",
			"min_talk_len": 5,
			"weights_file": "epoch-027.pkl"
		},
		"totals": {
			"selected": 75,
			"relevant": 5179,
			"true_positives": 2,
			"false_positives": 73,
			"false_negatives": 5177,
			"precision": 0.02666666666666667,
			"recall": 0.0003861749372465727,
			"f1_score": 0.0007613247049866769
		}
	},
	{
		"config": {
			"margin_of_error": [
				-0.5,
				0.5
			],
			"threshold": 0.6,
			"epoch": "best",
			"min_talk_len": 10,
			"weights_file": "epoch-027.pkl"
		},
		"totals": {
			"selected": 56,
			"relevant": 4767,
			"true_positives": 2,
			"false_positives": 54,
			"false_negatives": 4765,
			"precision": 0.03571428571428571,
			"recall": 0.0004195510803440319,
			"f1_score": 0.0008293593199253576
		}
	},
	{
		"config": {
			"margin_of_error": [
				-0.5,
				0.5
			],
			"threshold": 0.7,
			"epoch": "best",
			"min_talk_len": null,
			"weights_file": "epoch-027.pkl"
		},
		"totals": {
			"selected": 9,
			"relevant": 5744,
			"true_positives": 0,
			"false_positives": 9,
			"false_negatives": 5744,
			"precision": 0,
			"recall": 1,
			"f1_score": 0.0
		}
	},
	{
		"config": {
			"margin_of_error": [
				-0.5,
				0.5
			],
			"threshold": 0.7,
			"epoch": "best",
			"min_talk_len": 5,
			"weights_file": "epoch-027.pkl"
		},
		"totals": {
			"selected": 1,
			"relevant": 5179,
			"true_positives": 0,
			"false_positives": 1,
			"false_negatives": 5179,
			"precision": 0,
			"recall": 1,
			"f1_score": 0.0
		}
	},
	{
		"config": {
			"margin_of_error": [
				-0.5,
				0.5
			],
			"threshold": 0.7,
			"epoch": "best",
			"min_talk_len": 10,
			"weights_file": "epoch-027.pkl"
		},
		"totals": {
			"selected": 1,
			"relevant": 4767,
			"true_positives": 0,
			"false_positives": 1,
			"false_negatives": 4767,
			"precision": 0,
			"recall": 1,
			"f1_score": 0.0
		}
	},
	{
		"config": {
			"margin_of_error": [
				0,
				1
			],
			"threshold": 0.5,
			"epoch": "best",
			"min_talk_len": null,
			"weights_file": "epoch-027.pkl"
		},
		"totals": {
			"selected": 16646,
			"relevant": 5744,
			"true_positives": 903,
			"false_positives": 15743,
			"false_negatives": 4841,
			"precision": 0.05424726661059714,
			"recall": 0.15720752089136492,
			"f1_score": 0.08066100937918713
		}
	},
	{
		"config": {
			"margin_of_error": [
				0,
				1
			],
			"threshold": 0.5,
			"epoch": "best",
			"min_talk_len": 5,
			"weights_file": "epoch-027.pkl"
		},
		"totals": {
			"selected": 6861,
			"relevant": 5179,
			"true_positives": 804,
			"false_positives": 6057,
			"false_negatives": 4375,
			"precision": 0.11718408395277656,
			"recall": 0.15524232477312222,
			"f1_score": 0.1335548172757475
		}
	},
	{
		"config": {
			"margin_of_error": [
				0,
				1
			],
			"threshold": 0.5,
			"epoch": "best",
			"min_talk_len": 10,
			"weights_file": "epoch-027.pkl"
		},
		"totals": {
			"selected": 6058,
			"relevant": 4767,
			"true_positives": 749,
			"false_positives": 5309,
			"false_negatives": 4018,
			"precision": 0.1236381644106966,
			"recall": 0.15712187958883994,
			"f1_score": 0.13838337182448038
		}
	},
	{
		"config": {
			"margin_of_error": [
				0,
				1
			],
			"threshold": 0.6,
			"epoch": "best",
			"min_talk_len": null,
			"weights_file": "epoch-027.pkl"
		},
		"totals": {
			"selected": 350,
			"relevant": 5744,
			"true_positives": 8,
			"false_positives": 342,
			"false_negatives": 5736,
			"precision": 0.022857142857142857,
			"recall": 0.001392757660167131,
			"f1_score": 0.0026255333114538894
		}
	},
	{
		"config": {
			"margin_of_error": [
				0,
				1
			],
			"threshold": 0.6,
			"epoch": "best",
			"min_talk_len": 5,
			"weights_file": "epoch-027.pkl"
		},
		"totals": {
			"selected": 76,
			"relevant": 5179,
			"true_positives": 4,
			"false_positives": 72,
			"false_negatives": 5175,
			"precision": 0.05263157894736842,
			"recall": 0.0007723498744931454,
			"f1_score": 0.0015223596574690773
		}
	},
	{
		"config": {
			"margin_of_error": [
				0,
				1
			],
			"threshold": 0.6,
			"epoch": "best",
			"min_talk_len": 10,
			"weights_file": "epoch-027.pkl"
		},
		"totals": {
			"selected": 57,
			"relevant": 4767,
			"true_positives": 4,
			"false_positives": 53,
			"false_negatives": 4763,
			"precision": 0.07017543859649122,
			"recall": 0.0008391021606880638,
			"f1_score": 0.0016583747927031507
		}
	},
	{
		"config": {
			"margin_of_error": [
				0,
				1
			],
			"threshold": 0.7,
			"epoch": "best",
			"min_talk_len": null,
			"weights_file": "epoch-027.pkl"
		},
		"totals": {
			"selected": 9,
			"relevant": 5744,
			"true_positives": 0,
			"false_positives": 9,
			"false_negatives": 5744,
			"precision": 0,
			"recall": 1,
			"f1_score": 0.0
		}
	},
	{
		"config": {
			"margin_of_error": [
				0,
				1
			],
			"threshold": 0.7,
			"epoch": "best",
			"min_talk_len": 5,
			"weights_file": "epoch-027.pkl"
		},
		"totals": {
			"selected": 1,
			"relevant": 5179,
			"true_positives": 0,
			"false_positives": 1,
			"false_negatives": 5179,
			"precision": 0,
			"recall": 1,
			"f1_score": 0.0
		}
	},
	{
		"config": {
			"margin_of_error": [
				0,
				1
			],
			"threshold": 0.7,
			"epoch": "best",
			"min_talk_len": 10,
			"weights_file": "epoch-027.pkl"
		},
		"totals": {
			"selected": 1,
			"relevant": 4767,
			"true_positives": 0,
			"false_positives": 1,
			"false_negatives": 4767,
			"precision": 0,
			"recall": 1,
			"f1_score": 0.0
		}
	},
	{
		"config": {
			"margin_of_error": [
				-1,
				0
			],
			"threshold": 0.5,
			"epoch": "best",
			"min_talk_len": null,
			"weights_file": "epoch-027.pkl"
		},
		"totals": {
			"selected": 16646,
			"relevant": 5744,
			"true_positives": 159,
			"false_positives": 16487,
			"false_negatives": 5585,
			"precision": 0.009551844286915776,
			"recall": 0.027681058495821725,
			"f1_score": 0.014202769093345247
		}
	},
	{
		"config": {
			"margin_of_error": [
				-1,
				0
			],
			"threshold": 0.5,
			"epoch": "best",
			"min_talk_len": 5,
			"weights_file": "epoch-027.pkl"
		},
		"totals": {
			"selected": 6853,
			"relevant": 5179,
			"true_positives": 129,
			"false_positives": 6724,
			"false_negatives": 5050,
			"precision": 0.018823872756457027,
			"recall": 0.02490828345240394,
			"f1_score": 0.021442819148936174
		}
	},
	{
		"config": {
			"margin_of_error": [
				-1,
				0
			],
			"threshold": 0.5,
			"epoch": "best",
			"min_talk_len": 10,
			"weights_file": "epoch-027.pkl"
		},
		"totals": {
			"selected": 6051,
			"relevant": 4767,
			"true_positives": 116,
			"false_positives": 5935,
			"false_negatives": 4651,
			"precision": 0.019170385060320608,
			"recall": 0.02433396265995385,
			"f1_score": 0.021445738583841745
		}
	},
	{
		"config": {
			"margin_of_error": [
				-1,
				0
			],
			"threshold": 0.6,
			"epoch": "best",
			"min_talk_len": null,
			"weights_file": "epoch-027.pkl"
		},
		"totals": {
			"selected": 350,
			"relevant": 5744,
			"true_positives": 3,
			"false_positives": 347,
			"false_negatives": 5741,
			"precision": 0.008571428571428572,
			"recall": 0.0005222841225626741,
			"f1_score": 0.0009845749917952082
		}
	},
	{
		"config": {
			"margin_of_error": [
				-1,
				0
			],
			"threshold": 0.6,
			"epoch": "best",
			"min_talk_len": 5,
			"weights_file": "epoch-027.pkl"
		},
		"totals": {
			"selected": 75,
			"relevant": 5179,
			"true_positives": 3,
			"false_positives": 72,
			"false_negatives": 5176,
			"precision": 0.04,
			"recall": 0.0005792624058698591,
			"f1_score": 0.0011419870574800154
		}
	},
	{
		"config": {
			"margin_of_error": [
				-1,
				0
			],
			"threshold": 0.6,
			"epoch": "best",
			"min_talk_len": 10,
			"weights_file": "epoch-027.pkl"
		},
		"totals": {
			"selected": 56,
			"relevant": 4767,
			"true_positives": 3,
			"false_positives": 53,
			"false_negatives": 4764,
			"precision": 0.05357142857142857,
			"recall": 0.0006293266205160479,
			"f1_score": 0.0012440389798880364
		}
	},
	{
		"config": {
			"margin_of_error": [
				-1,
				0
			],
			"threshold": 0.7,
			"epoch": "best",
			"min_talk_len": null,
			"weights_file": "epoch-027.pkl"
		},
		"totals": {
			"selected": 9,
			"relevant": 5744,
			"true_positives": 0,
			"false_positives": 9,
			"false_negatives": 5744,
			"precision": 0,
			"recall": 1,
			"f1_score": 0.0
		}
	},
	{
		"config": {
			"margin_of_error": [
				-1,
				0
			],
			"threshold": 0.7,
			"epoch": "best",
			"min_talk_len": 5,
			"weights_file": "epoch-027.pkl"
		},
		"totals": {
			"selected": 1,
			"relevant": 5179,
			"true_positives": 0,
			"false_positives": 1,
			"false_negatives": 5179,
			"precision": 0,
			"recall": 1,
			"f1_score": 0.0
		}
	},
	{
		"config": {
			"margin_of_error": [
				-1,
				0
			],
			"threshold": 0.7,
			"epoch": "best",
			"min_talk_len": 10,
			"weights_file": "epoch-027.pkl"
		},
		"totals": {
			"selected": 1,
			"relevant": 4767,
			"true_positives": 0,
			"false_positives": 1,
			"false_negatives": 4767,
			"precision": 0,
			"recall": 1,
			"f1_score": 0.0
		}
	},
	{
		"config": {
			"margin_of_error": [
				-0.2,
				0.2
			],
			"threshold": 0.5,
			"epoch": "best",
			"min_talk_len": null,
			"weights_file": "epoch-027.pkl"
		},
		"totals": {
			"selected": 16646,
			"relevant": 5744,
			"true_positives": 125,
			"false_positives": 16521,
			"false_negatives": 5619,
			"precision": 0.007509311546317433,
			"recall": 0.02176183844011142,
			"f1_score": 0.011165698972755695
		}
	},
	{
		"config": {
			"margin_of_error": [
				-0.2,
				0.2
			],
			"threshold": 0.5,
			"epoch": "best",
			"min_talk_len": 5,
			"weights_file": "epoch-027.pkl"
		},
		"totals": {
			"selected": 6851,
			"relevant": 5179,
			"true_positives": 95,
			"false_positives": 6756,
			"false_negatives": 5084,
			"precision": 0.01386658881915049,
			"recall": 0.018343309519212203,
			"f1_score": 0.015793848711554447
		}
	},
	{
		"config": {
			"margin_of_error": [
				-0.2,
				0.2
			],
			"threshold": 0.5,
			"epoch": "best",
			"min_talk_len": 10,
			"weights_file": "epoch-027.pkl"
		},
		"totals": {
			"selected": 6051,
			"relevant": 4767,
			"true_positives": 87,
			"false_positives": 5964,
			"false_negatives": 4680,
			"precision": 0.014377788795240456,
			"recall": 0.01825047199496539,
			"f1_score": 0.01608430393788131
		}
	},
	{
		"config": {
			"margin_of_error": [
				-0.2,
				0.2
			],
			"threshold": 0.6,
			"epoch": "best",
			"min_talk_len": null,
			"weights_file": "epoch-027.pkl"
		},
		"totals": {
			"selected": 350,
			"relevant": 5744,
			"true_positives": 1,
			"false_positives": 349,
			"false_negatives": 5743,
			"precision": 0.002857142857142857,
			"recall": 0.00017409470752089137,
			"f1_score": 0.00032819166393173617
		}
	},
	{
		"config": {
			"margin_of_error": [
				-0.2,
				0.2
			],
			"threshold": 0.6,
			"epoch": "best",
			"min_talk_len": 5,
			"weights_file": "epoch-027.pkl"
		},
		"totals": {
			"selected": 75,
			"relevant": 5179,
			"true_positives": 0,
			"false_positives": 75,
			"false_negatives": 5179,
			"precision": 0,
			"recall": 1,
			"f1_score": 0.0
		}
	},
	{
		"config": {
			"margin_of_error": [
				-0.2,
				0.2
			],
			"threshold": 0.6,
			"epoch": "best",
			"min_talk_len": 10,
			"weights_file": "epoch-027.pkl"
		},
		"totals": {
			"selected": 56,
			"relevant": 4767,
			"true_positives": 0,
			"false_positives": 56,
			"false_negatives": 4767,
			"precision": 0,
			"recall": 1,
			"f1_score": 0.0
		}
	},
	{
		"config": {
			"margin_of_error": [
				-0.2,
				0.2
			],
			"threshold": 0.7,
			"epoch": "best",
			"min_talk_len": null,
			"weights_file": "epoch-027.pkl"
		},
		"totals": {
			"selected": 9,
			"relevant": 5744,
			"true_positives": 0,
			"false_positives": 9,
			"false_negatives": 5744,
			"precision": 0,
			"recall": 1,
			"f1_score": 0.0
		}
	},
	{
		"config": {
			"margin_of_error": [
				-0.2,
				0.2
			],
			"threshold": 0.7,
			"epoch": "best",
			"min_talk_len": 5,
			"weights_file": "epoch-027.pkl"
		},
		"totals": {
			"selected": 1,
			"relevant": 5179,
			"true_positives": 0,
			"false_positives": 1,
			"false_negatives": 5179,
			"precision": 0,
			"recall": 1,
			"f1_score": 0.0
		}
	},
	{
		"config": {
			"margin_of_error": [
				-0.2,
				0.2
			],
			"threshold": 0.7,
			"epoch": "best",
			"min_talk_len": 10,
			"weights_file": "epoch-027.pkl"
		},
		"totals": {
			"selected": 1,
			"relevant": 4767,
			"true_positives": 0,
			"false_positives": 1,
			"false_negatives": 4767,
			"precision": 0,
			"recall": 1,
			"f1_score": 0.0
		}
	}
]